[{"id": 0, "events": [{"name": "error", "freq": 1}, {"name": "closeErrorBox", "freq": 1}], "seqs": [120], "insert": [{"size": 0, "data": []}, {"size": 0, "data": []}, {"size": 0, "data": []}]}, {"id": 1, "events": [{"name": "treeStats", "freq": 1}], "seqs": [723], "insert": [{"size": 0, "data": []}, {"size": 0, "data": []}]}, {"id": 2, "events": [{"name": "load", "freq": 1}, {"name": "toolTip", "freq": 1}], "seqs": [910], "insert": [{"size": 0, "data": []}, {"size": 0, "data": []}, {"size": 0, "data": []}]}, {"id": 3, "events": [{"name": "create", "freq": 2}, {"name": "appInit", "freq": 3}, {"name": "resize", "freq": 3}, {"name": "treeStats", "freq": 3}, {"name": "resize", "freq": 3}, {"name": "treeStats", "freq": 3}, {"name": "readBoundData", "freq": 3}, {"name": "treeStats", "freq": 3}, {"name": "readBoundData", "freq": 3}, {"name": "treeStats", "freq": 3}, {"name": "readBoundData", "freq": 3}, {"name": "treeStats", "freq": 3}, {"name": "readBoundData", "freq": 3}, {"name": "readBoundData", "freq": 3}, {"name": "treeStats", "freq": 3}, {"name": "readBoundData", "freq": 3}, {"name": "readBoundData", "freq": 3}, {"name": "treeStats", "freq": 3}, {"name": "readBoundData", "freq": 3}, {"name": "treeStats", "freq": 3}, {"name": "readBoundData", "freq": 3}, {"name": "treeStats", "freq": 3}, {"name": "readBoundData", "freq": 3}, {"name": "readBoundData", "freq": 3}, {"name": "treeStats", "freq": 3}, {"name": "readBoundData", "freq": 3}, {"name": "treeStats", "freq": 3}, {"name": "readBoundData", "freq": 3}, {"name": "treeStats", "freq": 3}, {"name": "readBoundData", "freq": 3}, {"name": "treeStats", "freq": 3}, {"name": "readBoundData", "freq": 3}, {"name": "treeStats", "freq": 3}, {"name": "readBoundData", "freq": 3}, {"name": "readBoundData", "freq": 3}, {"name": "treeStats", "freq": 3}, {"name": "readBoundData", "freq": 3}, {"name": "readBoundData", "freq": 3}, {"name": "treeStats", "freq": 3}, {"name": "readBoundData", "freq": 3}, {"name": "treeStats", "freq": 3}, {"name": "readBoundData", "freq": 3}, {"name": "treeStats", "freq": 3}, {"name": "readBoundData", "freq": 3}, {"name": "treeStats", "freq": 3}, {"name": "readBoundData", "freq": 3}, {"name": "readBoundData", "freq": 3}, {"name": "treeStats", "freq": 3}, {"name": "readBoundData", "freq": 3}, {"name": "treeStats", "freq": 3}, {"name": "readBoundData", "freq": 3}, {"name": "treeStats", "freq": 3}, {"name": "readBoundData", "freq": 3}, {"name": "readBoundData", "freq": 3}, {"name": "treeStats", "freq": 3}, {"name": "readBoundData", "freq": 3}, {"name": "treeStats", "freq": 3}, {"name": "readBoundData", "freq": 3}, {"name": "readBoundData", "freq": 3}, {"name": "treeStats", "freq": 3}, {"name": "readBoundData", "freq": 3}, {"name": "treeStats", "freq": 3}, {"name": "readBoundData", "freq": 3}, {"name": "treeStats", "freq": 3}, {"name": "treeStats", "freq": 3}, {"name": "readBoundData", "freq": 3}, {"name": "treeStats", "freq": 3}, {"name": "readBoundData", "freq": 3}, {"name": "treeStats", "freq": 3}, {"name": "readBoundData", "freq": 3}, {"name": "treeStats", "freq": 3}, {"name": "readBoundData", "freq": 3}, {"name": "treeStats", "freq": 3}, {"name": "readBoundData", "freq": 3}, {"name": "treeStats", "freq": 3}, {"name": "readBoundData", "freq": 3}, {"name": "treeStats", "freq": 3}, {"name": "readBoundData", "freq": 3}, {"name": "treeStats", "freq": 3}, {"name": "readBoundData", "freq": 3}, {"name": "treeStats", "freq": 3}, {"name": "readBoundData", "freq": 3}, {"name": "readBoundData", "freq": 3}, {"name": "readBoundData", "freq": 3}, {"name": "treeStats", "freq": 3}, {"name": "readBoundData", "freq": 3}, {"name": "readBoundData", "freq": 3}, {"name": "treeStats", "freq": 3}, {"name": "readBoundData", "freq": 3}, {"name": "treeStats", "freq": 3}, {"name": "readBoundData", "freq": 3}, {"name": "treeStats", "freq": 3}, {"name": "treeStats", "freq": 3}, {"name": "readBoundData", "freq": 3}, {"name": "treeStats", "freq": 3}, {"name": "readBoundData", "freq": 3}, {"name": "treeStats", "freq": 3}, {"name": "readBoundData", "freq": 3}, {"name": "readBoundData", "freq": 3}, {"name": "treeStats", "freq": 3}, {"name": "readBoundData", "freq": 3}, {"name": "treeStats", "freq": 3}, {"name": "readBoundData", "freq": 3}, {"name": "readBoundData", "freq": 3}, {"name": "treeStats", "freq": 3}, {"name": "readBoundData", "freq": 3}, {"name": "resize", "freq": 3}, {"name": "readBoundData", "freq": 3}, {"name": "treeStats", "freq": 3}, {"name": "readBoundData", "freq": 3}, {"name": "treeStats", "freq": 3}, {"name": "readBoundData", "freq": 3}], "seqs": [125, 515, 523], "insert": [{"size": 0, "data": []}, {"size": 0, "data": []}, {"size": 15, "data": [{"name": "load", "freq": 1}, {"name": "treeStats", "freq": 10}, {"name": "warning", "freq": 8}, {"name": "readBoundData", "freq": 13}, {"name": "toolBarToggle", "freq": 2}, {"name": "toolTip", "freq": 6}, {"name": "resize", "freq": 3}, {"name": "closeErrorBox", "freq": 1}, {"name": "error", "freq": 1}, {"name": "writeSampleData2", "freq": 1}, {"name": "closeColorPicker", "freq": 1}, {"name": "pickedColor", "freq": 1}, {"name": "btColor", "freq": 1}, {"name": "bindFromPrompt", "freq": 1}, {"name": "create", "freq": 1}]}, {"size": 1, "data": [{"name": "readBoundData", "freq": 2}]}, {"size": 1, "data": [{"name": "readBoundData", "freq": 2}]}, {"size": 0, "data": []}, {"size": 0, "data": []}, {"size": 0, "data": []}, {"size": 0, "data": []}, {"size": 1, "data": [{"name": "warning", "freq": 1}]}, {"size": 0, "data": []}, {"size": 1, "data": [{"name": "warning", "freq": 1}]}, {"size": 0, "data": []}, {"size": 2, "data": [{"name": "warning", "freq": 1}, {"name": "treeStats", "freq": 2}]}, {"size": 1, "data": [{"name": "warning", "freq": 1}]}, {"size": 0, "data": []}, {"size": 2, "data": [{"name": "warning", "freq": 1}, {"name": "treeStats", "freq": 2}]}, {"size": 1, "data": [{"name": "warning", "freq": 1}]}, {"size": 0, "data": []}, {"size": 1, "data": [{"name": "warning", "freq": 1}]}, {"size": 0, "data": []}, {"size": 0, "data": []}, {"size": 1, "data": [{"name": "warning", "freq": 1}]}, {"size": 2, "data": [{"name": "warning", "freq": 1}, {"name": "treeStats", "freq": 2}]}, {"size": 0, "data": []}, {"size": 0, "data": []}, {"size": 1, "data": [{"name": "warning", "freq": 1}]}, {"size": 0, "data": []}, {"size": 1, "data": [{"name": "warning", "freq": 1}]}, {"size": 0, "data": []}, {"size": 1, "data": [{"name": "warning", "freq": 1}]}, {"size": 0, "data": []}, {"size": 1, "data": [{"name": "warning", "freq": 1}]}, {"size": 0, "data": []}, {"size": 2, "data": [{"name": "warning", "freq": 1}, {"name": "treeStats", "freq": 2}]}, {"size": 0, "data": []}, {"size": 0, "data": []}, {"size": 2, "data": [{"name": "warning", "freq": 1}, {"name": "treeStats", "freq": 2}]}, {"size": 0, "data": []}, {"size": 0, "data": []}, {"size": 1, "data": [{"name": "warning", "freq": 1}]}, {"size": 0, "data": []}, {"size": 1, "data": [{"name": "warning", "freq": 1}]}, {"size": 0, "data": []}, {"size": 1, "data": [{"name": "warning", "freq": 1}]}, {"size": 0, "data": []}, {"size": 2, "data": [{"name": "warning", "freq": 1}, {"name": "treeStats", "freq": 2}]}, {"size": 0, "data": []}, {"size": 1, "data": [{"name": "warning", "freq": 1}]}, {"size": 0, "data": []}, {"size": 0, "data": []}, {"size": 1, "data": [{"name": "warning", "freq": 1}]}, {"size": 0, "data": []}, {"size": 2, "data": [{"name": "warning", "freq": 1}, {"name": "treeStats", "freq": 2}]}, {"size": 0, "data": []}, {"size": 0, "data": []}, {"size": 0, "data": []}, {"size": 0, "data": []}, {"size": 2, "data": [{"name": "resize", "freq": 1}, {"name": "treeStats", "freq": 2}]}, {"size": 0, "data": []}, {"size": 0, "data": []}, {"size": 0, "data": []}, {"size": 0, "data": []}, {"size": 0, "data": []}, {"size": 3, "data": [{"name": "resize", "freq": 3}, {"name": "appInit", "freq": 2}, {"name": "readBoundData", "freq": 2}]}, {"size": 0, "data": []}, {"size": 0, "data": []}, {"size": 0, "data": []}, {"size": 0, "data": []}, {"size": 0, "data": []}, {"size": 0, "data": []}, {"size": 0, "data": []}, {"size": 0, "data": []}, {"size": 0, "data": []}, {"size": 0, "data": []}, {"size": 0, "data": []}, {"size": 2, "data": [{"name": "appInit", "freq": 1}, {"name": "resize", "freq": 1}]}, {"size": 0, "data": []}, {"size": 0, "data": []}, {"size": 0, "data": []}, {"size": 0, "data": []}, {"size": 0, "data": []}, {"size": 4, "data": [{"name": "load", "freq": 2}, {"name": "appInit", "freq": 1}, {"name": "resize", "freq": 1}, {"name": "treeStats", "freq": 2}]}, {"size": 3, "data": [{"name": "resize", "freq": 1}, {"name": "load", "freq": 1}, {"name": "treeStats", "freq": 2}]}, {"size": 0, "data": []}, {"size": 2, "data": [{"name": "resize", "freq": 2}, {"name": "appInit", "freq": 1}]}, {"size": 2, "data": [{"name": "warning", "freq": 1}, {"name": "treeStats", "freq": 2}]}, {"size": 2, "data": [{"name": "resize", "freq": 1}, {"name": "warning", "freq": 1}]}, {"size": 0, "data": []}, {"size": 0, "data": []}, {"size": 0, "data": []}, {"size": 0, "data": []}, {"size": 4, "data": [{"name": "appInit", "freq": 1}, {"name": "setTitle", "freq": 2}, {"name": "toolTip", "freq": 3}, {"name": "readBoundData", "freq": 1}]}, {"size": 0, "data": []}, {"size": 0, "data": []}, {"size": 0, "data": []}, {"size": 0, "data": []}, {"size": 0, "data": []}, {"size": 2, "data": [{"name": "resize", "freq": 1}, {"name": "treeStats", "freq": 2}]}, {"size": 0, "data": []}, {"size": 0, "data": []}, {"size": 0, "data": []}, {"size": 0, "data": []}, {"size": 2, "data": [{"name": "resize", "freq": 1}, {"name": "treeStats", "freq": 2}]}, {"size": 2, "data": [{"name": "resize", "freq": 4}, {"name": "appInit", "freq": 4}]}, {"size": 2, "data": [{"name": "appInit", "freq": 1}, {"name": "resize", "freq": 1}]}, {"size": 4, "data": [{"name": "load", "freq": 4}, {"name": "appInit", "freq": 2}, {"name": "treeStats", "freq": 2}, {"name": "error", "freq": 2}]}, {"size": 0, "data": []}, {"size": 1, "data": [{"name": "resize", "freq": 1}]}, {"size": 0, "data": []}, {"size": 0, "data": []}, {"size": 0, "data": []}, {"size": 1, "data": [{"name": "resize", "freq": 1}]}]}, {"id": 4, "events": [{"name": "appInit", "freq": 12}, {"name": "create", "freq": 9}, {"name": "resize", "freq": 13}, {"name": "treeStats", "freq": 12}, {"name": "readBoundData", "freq": 13}, {"name": "treeStats", "freq": 13}, {"name": "readBoundData", "freq": 13}, {"name": "treeStats", "freq": 13}, {"name": "readBoundData", "freq": 13}, {"name": "treeStats", "freq": 13}, {"name": "readBoundData", "freq": 13}, {"name": "treeStats", "freq": 13}, {"name": "readBoundData", "freq": 12}, {"name": "readBoundData", "freq": 11}, {"name": "readBoundData", "freq": 13}, {"name": "treeStats", "freq": 12}, {"name": "readBoundData", "freq": 13}, {"name": "treeStats", "freq": 11}, {"name": "readBoundData", "freq": 13}, {"name": "treeStats", "freq": 11}, {"name": "readBoundData", "freq": 11}, {"name": "readBoundData", "freq": 13}, {"name": "treeStats", "freq": 12}, {"name": "readBoundData", "freq": 9}], "seqs": [72, 126, 127, 133, 139, 504, 558, 585, 586, 593, 711, 820, 971], "insert": [{"size": 7, "data": [{"name": "appInit", "freq": 16}, {"name": "load", "freq": 5}, {"name": "resize", "freq": 14}, {"name": "treeStats", "freq": 16}, {"name": "readBoundData", "freq": 18}, {"name": "warning", "freq": 4}, {"name": "create", "freq": 4}]}, {"size": 0, "data": []}, {"size": 13, "data": [{"name": "load", "freq": 3}, {"name": "warning", "freq": 5}, {"name": "readBoundData", "freq": 22}, {"name": "resize", "freq": 4}, {"name": "toolBarToggle", "freq": 1}, {"name": "treeStats", "freq": 19}, {"name": "bindFromPrompt", "freq": 11}, {"name": "toolTip", "freq": 10}, {"name": "closeErrorBox", "freq": 5}, {"name": "pickedColor", "freq": 3}, {"name": "btColor", "freq": 3}, {"name": "error", "freq": 2}, {"name": "writeSampleData2", "freq": 1}]}, {"size": 8, "data": [{"name": "readBoundData", "freq": 16}, {"name": "closeErrorBox", "freq": 1}, {"name": "warning", "freq": 3}, {"name": "treeStats", "freq": 10}, {"name": "bindFromPrompt", "freq": 5}, {"name": "create", "freq": 2}, {"name": "toolTip", "freq": 2}, {"name": "toolBarToggle", "freq": 1}]}, {"size": 12, "data": [{"name": "resize", "freq": 4}, {"name": "pickedColor", "freq": 1}, {"name": "toolTip", "freq": 3}, {"name": "btColor", "freq": 1}, {"name": "writeSampleData", "freq": 2}, {"name": "readBoundData", "freq": 2}, {"name": "warning", "freq": 1}, {"name": "bindFromPrompt", "freq": 3}, {"name": "closeColorPicker", "freq": 1}, {"name": "writeSampleData2", "freq": 1}, {"name": "closeErrorBox", "freq": 1}, {"name": "error", "freq": 1}]}, {"size": 1, "data": [{"name": "warning", "freq": 1}]}, {"size": 12, "data": [{"name": "resize", "freq": 7}, {"name": "readBoundData", "freq": 7}, {"name": "warning", "freq": 3}, {"name": "error", "freq": 6}, {"name": "pickedColor", "freq": 8}, {"name": "toolTip", "freq": 7}, {"name": "closeErrorBox", "freq": 3}, {"name": "writeSampleData2", "freq": 1}, {"name": "closeColorPicker", "freq": 1}, {"name": "btColor", "freq": 4}, {"name": "toolBarToggle", "freq": 2}, {"name": "writeSampleData", "freq": 1}]}, {"size": 7, "data": [{"name": "resize", "freq": 2}, {"name": "toolTip", "freq": 1}, {"name": "pickedColor", "freq": 1}, {"name": "btColor", "freq": 1}, {"name": "appInit", "freq": 1}, {"name": "treeStats", "freq": 1}, {"name": "closeErrorBox", "freq": 1}]}, {"size": 4, "data": [{"name": "resize", "freq": 4}, {"name": "toolTip", "freq": 3}, {"name": "readBoundData", "freq": 3}, {"name": "bindFromPrompt", "freq": 1}]}, {"size": 5, "data": [{"name": "warning", "freq": 1}, {"name": "error", "freq": 2}, {"name": "toolTip", "freq": 2}, {"name": "writeSampleData", "freq": 2}, {"name": "treeStats", "freq": 2}]}, {"size": 4, "data": [{"name": "pickedColor", "freq": 1}, {"name": "btColor", "freq": 1}, {"name": "resize", "freq": 1}, {"name": "readBoundData", "freq": 1}]}, {"size": 6, "data": [{"name": "resize", "freq": 4}, {"name": "appInit", "freq": 4}, {"name": "load", "freq": 1}, {"name": "treeStats", "freq": 2}, {"name": "toolTip", "freq": 2}, {"name": "closeColorPicker", "freq": 1}]}, {"size": 9, "data": [{"name": "toolBarToggle", "freq": 2}, {"name": "readBoundData", "freq": 2}, {"name": "bindFromPrompt", "freq": 2}, {"name": "closeColorPicker", "freq": 1}, {"name": "pickedColor", "freq": 1}, {"name": "btColor", "freq": 1}, {"name": "toolTip", "freq": 3}, {"name": "error", "freq": 2}, {"name": "resize", "freq": 2}]}, {"size": 6, "data": [{"name": "toolTip", "freq": 2}, {"name": "treeStats", "freq": 8}, {"name": "resize", "freq": 3}, {"name": "load", "freq": 2}, {"name": "appInit", "freq": 1}, {"name": "warning", "freq": 2}]}, {"size": 7, "data": [{"name": "treeStats", "freq": 7}, {"name": "resize", "freq": 2}, {"name": "load", "freq": 1}, {"name": "error", "freq": 1}, {"name": "toolTip", "freq": 2}, {"name": "warning", "freq": 1}, {"name": "bindFromPrompt", "freq": 1}]}, {"size": 1, "data": [{"name": "warning", "freq": 2}]}, {"size": 13, "data": [{"name": "resize", "freq": 4}, {"name": "appInit", "freq": 2}, {"name": "load", "freq": 1}, {"name": "closeAboutBox", "freq": 1}, {"name": "toolTip", "freq": 2}, {"name": "aboutBox", "freq": 1}, {"name": "error", "freq": 2}, {"name": "bindFromPrompt", "freq": 1}, {"name": "closeColorPicker", "freq": 1}, {"name": "pickedColor", "freq": 1}, {"name": "btColor", "freq": 1}, {"name": "toolBarToggle", "freq": 1}, {"name": "readBoundData", "freq": 1}]}, {"size": 5, "data": [{"name": "appInit", "freq": 5}, {"name": "resize", "freq": 4}, {"name": "load", "freq": 1}, {"name": "toolTip", "freq": 1}, {"name": "warning", "freq": 1}]}, {"size": 11, "data": [{"name": "resize", "freq": 7}, {"name": "readBoundData", "freq": 7}, {"name": "appInit", "freq": 1}, {"name": "warning", "freq": 2}, {"name": "toolTip", "freq": 4}, {"name": "writeSampleData", "freq": 1}, {"name": "error", "freq": 2}, {"name": "writeSampleData2", "freq": 1}, {"name": "bindFromPrompt", "freq": 1}, {"name": "toolBarToggle", "freq": 1}, {"name": "setTitle", "freq": 1}]}, {"size": 7, "data": [{"name": "warning", "freq": 2}, {"name": "resize", "freq": 3}, {"name": "appInit", "freq": 1}, {"name": "load", "freq": 1}, {"name": "treeStats", "freq": 1}, {"name": "toolTip", "freq": 2}, {"name": "pickedColor", "freq": 1}]}, {"size": 5, "data": [{"name": "resize", "freq": 3}, {"name": "readBoundData", "freq": 2}, {"name": "pickedColor", "freq": 1}, {"name": "toolTip", "freq": 1}, {"name": "error", "freq": 1}]}, {"size": 4, "data": [{"name": "treeStats", "freq": 5}, {"name": "warning", "freq": 3}, {"name": "toolTip", "freq": 1}, {"name": "resize", "freq": 2}]}, {"size": 1, "data": [{"name": "warning", "freq": 2}]}, {"size": 9, "data": [{"name": "appInit", "freq": 5}, {"name": "resize", "freq": 4}, {"name": "load", "freq": 2}, {"name": "readBoundData", "freq": 2}, {"name": "warning", "freq": 1}, {"name": "error", "freq": 1}, {"name": "closeAboutBox", "freq": 1}, {"name": "aboutBox", "freq": 1}, {"name": "toolTip", "freq": 1}]}, {"size": 11, "data": [{"name": "resize", "freq": 8}, {"name": "load", "freq": 1}, {"name": "toolBarToggle", "freq": 1}, {"name": "treeStats", "freq": 3}, {"name": "closeAboutBox", "freq": 1}, {"name": "toolTip", "freq": 3}, {"name": "aboutBox", "freq": 1}, {"name": "warning", "freq": 1}, {"name": "pickedColor", "freq": 1}, {"name": "error", "freq": 1}, {"name": "appInit", "freq": 1}]}]}, {"id": 5, "events": [{"name": "toolBarToggle", "freq": 2}, {"name": "toolTip", "freq": 2}, {"name": "toolBarToggle", "freq": 2}], "seqs": [174, 803], "insert": [{"size": 4, "data": [{"name": "toolBarToggle", "freq": 2}, {"name": "appInit", "freq": 2}, {"name": "resize", "freq": 1}, {"name": "create", "freq": 1}]}, {"size": 0, "data": []}, {"size": 3, "data": [{"name": "pickedColor", "freq": 1}, {"name": "btColor", "freq": 1}, {"name": "resize", "freq": 1}]}, {"size": 2, "data": [{"name": "load", "freq": 1}, {"name": "toolTip", "freq": 1}]}]}, {"id": 6, "events": [{"name": "aboutBox", "freq": 1}, {"name": "toolTip", "freq": 2}, {"name": "resize", "freq": 2}], "seqs": [509, 510], "insert": [{"size": 0, "data": []}, {"size": 0, "data": []}, {"size": 1, "data": [{"name": "closeAboutBox", "freq": 1}]}, {"size": 0, "data": []}]}, {"id": 7, "events": [{"name": "readBoundData", "freq": 2}, {"name": "resize", "freq": 2}], "seqs": [181, 721], "insert": [{"size": 2, "data": [{"name": "readBoundData", "freq": 1}, {"name": "toolTip", "freq": 1}]}, {"size": 0, "data": []}, {"size": 1, "data": [{"name": "treeStats", "freq": 1}]}]}, {"id": 8, "events": [{"name": "toolTip", "freq": 3}, {"name": "pickedColor", "freq": 2}], "seqs": [581, 766, 767], "insert": [{"size": 21, "data": [{"name": "toolTip", "freq": 15}, {"name": "pickedColor", "freq": 3}, {"name": "btColor", "freq": 3}, {"name": "cbPercent", "freq": 4}, {"name": "tbBins", "freq": 3}, {"name": "setTitle", "freq": 4}, {"name": "slider", "freq": 7}, {"name": "resize", "freq": 15}, {"name": "cbCategory", "freq": 4}, {"name": "readBoundData", "freq": 4}, {"name": "bindFromPrompt", "freq": 2}, {"name": "btSetData", "freq": 2}, {"name": "create", "freq": 2}, {"name": "appInit", "freq": 6}, {"name": "toolBarToggle", "freq": 5}, {"name": "load", "freq": 2}, {"name": "closeAboutBox", "freq": 1}, {"name": "aboutBox", "freq": 1}, {"name": "closeErrorBox", "freq": 1}, {"name": "error", "freq": 1}, {"name": "writeSampleData", "freq": 1}]}, {"size": 0, "data": []}, {"size": 7, "data": [{"name": "readBoundData", "freq": 6}, {"name": "resize", "freq": 18}, {"name": "appInit", "freq": 12}, {"name": "load", "freq": 6}, {"name": "toolBarToggle", "freq": 4}, {"name": "setTitle", "freq": 2}, {"name": "tbBins", "freq": 1}]}]}, {"id": 9, "events": [{"name": "resize", "freq": 2}, {"name": "toolTip", "freq": 3}], "seqs": [2, 553, 732, 932], "insert": [{"size": 18, "data": [{"name": "toolBarToggle", "freq": 1}, {"name": "toolTip", "freq": 7}, {"name": "resize", "freq": 7}, {"name": "create", "freq": 2}, {"name": "appInit", "freq": 2}, {"name": "load", "freq": 1}, {"name": "readBoundData", "freq": 4}, {"name": "setTitle", "freq": 1}, {"name": "cbCategory", "freq": 2}, {"name": "cbPercent", "freq": 2}, {"name": "slider", "freq": 2}, {"name": "closeErrorBox", "freq": 1}, {"name": "warning", "freq": 1}, {"name": "bindFromPrompt", "freq": 2}, {"name": "btSetData", "freq": 1}, {"name": "treeStats", "freq": 1}, {"name": "writeSampleData", "freq": 1}, {"name": "pickedColor", "freq": 1}]}, {"size": 0, "data": []}, {"size": 2, "data": [{"name": "pickedColor", "freq": 1}, {"name": "btColor", "freq": 1}]}]}, {"id": 10, "events": [{"name": "create", "freq": 35}, {"name": "appInit", "freq": 36}, {"name": "resize", "freq": 43}, {"name": "treeStats", "freq": 34}, {"name": "bindFromPrompt", "freq": 32}, {"name": "readBoundData", "freq": 43}, {"name": "treeStats", "freq": 39}, {"name": "readBoundData", "freq": 43}, {"name": "treeStats", "freq": 37}, {"name": "readBoundData", "freq": 35}, {"name": "readBoundData", "freq": 38}, {"name": "treeStats", "freq": 34}, {"name": "readBoundData", "freq": 35}], "seqs": [24, 61, 63, 68, 71, 92, 104, 111, 112, 116, 137, 140, 143, 145, 149, 187, 188, 254, 262, 285, 298, 354, 360, 361, 362, 376, 378, 387, 404, 494, 544, 574, 590, 681, 741, 773, 836, 851, 937, 939, 944, 945, 957, 966], "insert": [{"size": 13, "data": [{"name": "create", "freq": 15}, {"name": "appInit", "freq": 8}, {"name": "load", "freq": 3}, {"name": "treeStats", "freq": 7}, {"name": "warning", "freq": 1}, {"name": "readBoundData", "freq": 4}, {"name": "closeErrorBox", "freq": 1}, {"name": "error", "freq": 1}, {"name": "resize", "freq": 8}, {"name": "writeSampleData2", "freq": 1}, {"name": "toolTip", "freq": 4}, {"name": "writeSampleData", "freq": 1}, {"name": "toolBarToggle", "freq": 2}]}, {"size": 0, "data": []}, {"size": 9, "data": [{"name": "load", "freq": 4}, {"name": "create", "freq": 16}, {"name": "closeErrorBox", "freq": 1}, {"name": "resize", "freq": 7}, {"name": "toolTip", "freq": 3}, {"name": "writeSampleData", "freq": 1}, {"name": "error", "freq": 1}, {"name": "readBoundData", "freq": 3}, {"name": "pickedColor", "freq": 1}]}, {"size": 13, "data": [{"name": "readBoundData", "freq": 11}, {"name": "treeStats", "freq": 5}, {"name": "writeSampleData", "freq": 2}, {"name": "pickedColor", "freq": 2}, {"name": "toolTip", "freq": 8}, {"name": "btColor", "freq": 2}, {"name": "btSetData", "freq": 5}, {"name": "appInit", "freq": 2}, {"name": "toolBarToggle", "freq": 2}, {"name": "error", "freq": 3}, {"name": "cbCategory", "freq": 1}, {"name": "closeErrorBox", "freq": 1}, {"name": "bindFromPrompt", "freq": 2}]}, {"size": 17, "data": [{"name": "toolTip", "freq": 16}, {"name": "closeErrorBox", "freq": 4}, {"name": "error", "freq": 4}, {"name": "writeSampleData2", "freq": 4}, {"name": "resize", "freq": 10}, {"name": "closeAboutBox", "freq": 1}, {"name": "aboutBox", "freq": 1}, {"name": "closeColorPicker", "freq": 1}, {"name": "btColor", "freq": 2}, {"name": "writeSampleData", "freq": 2}, {"name": "create", "freq": 1}, {"name": "readBoundData", "freq": 7}, {"name": "load", "freq": 3}, {"name": "appInit", "freq": 1}, {"name": "pickedColor", "freq": 1}, {"name": "toolBarToggle", "freq": 2}, {"name": "warning", "freq": 1}]}, {"size": 23, "data": [{"name": "toolTip", "freq": 26}, {"name": "error", "freq": 21}, {"name": "closeErrorBox", "freq": 12}, {"name": "readBoundData", "freq": 58}, {"name": "warning", "freq": 20}, {"name": "treeStats", "freq": 35}, {"name": "resize", "freq": 17}, {"name": "appInit", "freq": 7}, {"name": "cbPercent", "freq": 2}, {"name": "cbCategory", "freq": 1}, {"name": "pickedColor", "freq": 7}, {"name": "btColor", "freq": 4}, {"name": "toolBarToggle", "freq": 6}, {"name": "slider", "freq": 1}, {"name": "writeSampleData2", "freq": 4}, {"name": "load", "freq": 8}, {"name": "yCbCategory", "freq": 2}, {"name": "xSlider", "freq": 1}, {"name": "writeSampleData", "freq": 3}, {"name": "closeAboutBox", "freq": 2}, {"name": "aboutBox", "freq": 2}, {"name": "closeColorPicker", "freq": 1}, {"name": "setTitle", "freq": 1}]}, {"size": 21, "data": [{"name": "resize", "freq": 10}, {"name": "create", "freq": 1}, {"name": "load", "freq": 2}, {"name": "appInit", "freq": 2}, {"name": "treeStats", "freq": 4}, {"name": "pickedColor", "freq": 2}, {"name": "toolTip", "freq": 10}, {"name": "btColor", "freq": 3}, {"name": "warning", "freq": 2}, {"name": "slider", "freq": 2}, {"name": "cbCategory", "freq": 2}, {"name": "cbPercent", "freq": 2}, {"name": "toolBarToggle", "freq": 1}, {"name": "aboutBox", "freq": 1}, {"name": "writeSampleData", "freq": 1}, {"name": "error", "freq": 1}, {"name": "closeColorPicker", "freq": 1}, {"name": "setTitle", "freq": 2}, {"name": "xCbCategory", "freq": 2}, {"name": "ySlider", "freq": 1}, {"name": "xSlider", "freq": 1}]}, {"size": 17, "data": [{"name": "warning", "freq": 2}, {"name": "error", "freq": 10}, {"name": "resize", "freq": 11}, {"name": "toolTip", "freq": 17}, {"name": "readBoundData", "freq": 11}, {"name": "writeSampleData", "freq": 1}, {"name": "writeSampleData2", "freq": 1}, {"name": "closeAboutBox", "freq": 3}, {"name": "aboutBox", "freq": 2}, {"name": "pickedColor", "freq": 6}, {"name": "btColor", "freq": 4}, {"name": "toolBarToggle", "freq": 3}, {"name": "load", "freq": 3}, {"name": "appInit", "freq": 2}, {"name": "closeErrorBox", "freq": 2}, {"name": "setTitle", "freq": 3}, {"name": "create", "freq": 2}]}, {"size": 17, "data": [{"name": "resize", "freq": 9}, {"name": "writeSampleData2", "freq": 1}, {"name": "error", "freq": 3}, {"name": "toolTip", "freq": 11}, {"name": "load", "freq": 1}, {"name": "treeStats", "freq": 2}, {"name": "closeErrorBox", "freq": 2}, {"name": "warning", "freq": 5}, {"name": "closeColorPicker", "freq": 2}, {"name": "closeAboutBox", "freq": 1}, {"name": "aboutBox", "freq": 1}, {"name": "pickedColor", "freq": 3}, {"name": "btColor", "freq": 3}, {"name": "toolBarToggle", "freq": 5}, {"name": "cbCategory", "freq": 2}, {"name": "cbPercent", "freq": 1}, {"name": "setTitle", "freq": 1}]}, {"size": 18, "data": [{"name": "toolTip", "freq": 14}, {"name": "readBoundData", "freq": 15}, {"name": "resize", "freq": 4}, {"name": "load", "freq": 3}, {"name": "appInit", "freq": 3}, {"name": "writeSampleData", "freq": 3}, {"name": "error", "freq": 7}, {"name": "writeSampleData2", "freq": 1}, {"name": "warning", "freq": 5}, {"name": "pickedColor", "freq": 4}, {"name": "bindFromPrompt", "freq": 1}, {"name": "closeAboutBox", "freq": 1}, {"name": "aboutBox", "freq": 1}, {"name": "closeErrorBox", "freq": 2}, {"name": "slider", "freq": 2}, {"name": "toolBarToggle", "freq": 1}, {"name": "setTitle", "freq": 3}, {"name": "btColor", "freq": 1}]}, {"size": 18, "data": [{"name": "treeStats", "freq": 16}, {"name": "closeColorPicker", "freq": 2}, {"name": "btColor", "freq": 6}, {"name": "pickedColor", "freq": 6}, {"name": "resize", "freq": 7}, {"name": "closeAboutBox", "freq": 2}, {"name": "toolTip", "freq": 12}, {"name": "aboutBox", "freq": 2}, {"name": "warning", "freq": 5}, {"name": "closeErrorBox", "freq": 2}, {"name": "error", "freq": 3}, {"name": "setTitle", "freq": 1}, {"name": "appInit", "freq": 1}, {"name": "load", "freq": 1}, {"name": "ySlider", "freq": 1}, {"name": "xTbBins", "freq": 1}, {"name": "xSlider", "freq": 1}, {"name": "writeSampleData2", "freq": 1}]}, {"size": 14, "data": [{"name": "toolTip", "freq": 10}, {"name": "error", "freq": 2}, {"name": "closeAboutBox", "freq": 1}, {"name": "aboutBox", "freq": 1}, {"name": "closeColorPicker", "freq": 2}, {"name": "btColor", "freq": 2}, {"name": "warning", "freq": 3}, {"name": "resize", "freq": 6}, {"name": "appInit", "freq": 1}, {"name": "treeStats", "freq": 3}, {"name": "writeSampleData2", "freq": 1}, {"name": "writeSampleData", "freq": 2}, {"name": "toolBarToggle", "freq": 3}, {"name": "setTitle", "freq": 1}]}, {"size": 11, "data": [{"name": "error", "freq": 2}, {"name": "toolTip", "freq": 2}, {"name": "warning", "freq": 1}, {"name": "readBoundData", "freq": 4}, {"name": "resize", "freq": 6}, {"name": "appInit", "freq": 3}, {"name": "load", "freq": 4}, {"name": "pickedColor", "freq": 2}, {"name": "btColor", "freq": 2}, {"name": "closeColorPicker", "freq": 1}, {"name": "closeErrorBox", "freq": 1}]}, {"size": 12, "data": [{"name": "resize", "freq": 11}, {"name": "error", "freq": 1}, {"name": "pickedColor", "freq": 2}, {"name": "toolTip", "freq": 8}, {"name": "load", "freq": 3}, {"name": "appInit", "freq": 3}, {"name": "treeStats", "freq": 8}, {"name": "toolBarToggle", "freq": 8}, {"name": "closeErrorBox", "freq": 3}, {"name": "warning", "freq": 3}, {"name": "btColor", "freq": 1}, {"name": "writeSampleData", "freq": 1}]}]}, {"id": 11, "events": [{"name": "readBoundData", "freq": 8}, {"name": "treeStats", "freq": 7}, {"name": "readBoundData", "freq": 8}], "seqs": [59, 575, 584, 587, 677, 844, 933, 979], "insert": [{"size": 10, "data": [{"name": "readBoundData", "freq": 19}, {"name": "setTitle", "freq": 3}, {"name": "resize", "freq": 5}, {"name": "treeStats", "freq": 7}, {"name": "toolTip", "freq": 5}, {"name": "error", "freq": 2}, {"name": "bindFromPrompt", "freq": 1}, {"name": "appInit", "freq": 4}, {"name": "toolBarToggle", "freq": 1}, {"name": "warning", "freq": 4}]}, {"size": 0, "data": []}, {"size": 2, "data": [{"name": "resize", "freq": 1}, {"name": "toolTip", "freq": 1}]}, {"size": 9, "data": [{"name": "setTitle", "freq": 1}, {"name": "resize", "freq": 3}, {"name": "load", "freq": 1}, {"name": "pickedColor", "freq": 1}, {"name": "btColor", "freq": 1}, {"name": "toolTip", "freq": 4}, {"name": "toolBarToggle", "freq": 2}, {"name": "closeColorPicker", "freq": 1}, {"name": "treeStats", "freq": 2}]}]}, {"id": 12, "events": [{"name": "toolTip", "freq": 2}], "seqs": [265, 582], "insert": [{"size": 0, "data": []}, {"size": 0, "data": []}]}, {"id": 13, "events": [{"name": "readBoundData", "freq": 13}], "seqs": [90, 119, 179, 323, 324, 337, 338, 483, 491, 499, 501, 555, 783, 846, 975], "insert": [{"size": 9, "data": [{"name": "resize", "freq": 5}, {"name": "toolTip", "freq": 1}, {"name": "pickedColor", "freq": 1}, {"name": "readBoundData", "freq": 13}, {"name": "error", "freq": 1}, {"name": "appInit", "freq": 3}, {"name": "treeStats", "freq": 3}, {"name": "warning", "freq": 6}, {"name": "load", "freq": 3}]}, {"size": 0, "data": []}]}, {"id": 14, "events": [{"name": "appInit", "freq": 24}], "seqs": [30, 259, 272, 278, 279, 457, 468, 475, 576, 577, 578, 595, 606, 607, 646, 686, 687, 688, 716, 804, 927, 928, 929, 997], "insert": [{"size": 0, "data": []}, {"size": 0, "data": []}]}, {"id": 15, "events": [{"name": "create", "freq": 46}, {"name": "appInit", "freq": 41}, {"name": "resize", "freq": 45}, {"name": "btSetData", "freq": 36}, {"name": "bindFromPrompt", "freq": 44}, {"name": "error", "freq": 44}, {"name": "closeErrorBox", "freq": 43}, {"name": "toolTip", "freq": 32}, {"name": "toolTip", "freq": 34}], "seqs": [76, 79, 81, 98, 152, 182, 184, 197, 198, 215, 219, 224, 230, 264, 292, 296, 301, 371, 394, 456, 465, 466, 485, 486, 495, 496, 522, 524, 548, 564, 572, 638, 655, 656, 661, 689, 733, 734, 792, 794, 839, 874, 907, 908, 940, 992], "insert": [{"size": 3, "data": [{"name": "create", "freq": 8}, {"name": "appInit", "freq": 5}, {"name": "resize", "freq": 2}]}, {"size": 0, "data": []}, {"size": 4, "data": [{"name": "load", "freq": 1}, {"name": "treeStats", "freq": 2}, {"name": "create", "freq": 3}, {"name": "resize", "freq": 1}]}, {"size": 12, "data": [{"name": "toolTip", "freq": 18}, {"name": "writeSampleData", "freq": 5}, {"name": "cbPercent", "freq": 1}, {"name": "cbCategory", "freq": 2}, {"name": "setTitle", "freq": 2}, {"name": "slider", "freq": 5}, {"name": "toolBarToggle", "freq": 8}, {"name": "appInit", "freq": 1}, {"name": "treeStats", "freq": 3}, {"name": "closeErrorBox", "freq": 1}, {"name": "error", "freq": 1}, {"name": "writeSampleData2", "freq": 1}]}, {"size": 2, "data": [{"name": "toolTip", "freq": 2}, {"name": "resize", "freq": 2}]}, {"size": 13, "data": [{"name": "slider", "freq": 8}, {"name": "readBoundData", "freq": 10}, {"name": "toolTip", "freq": 16}, {"name": "pickedColor", "freq": 4}, {"name": "btColor", "freq": 3}, {"name": "tbBins", "freq": 2}, {"name": "cbPercent", "freq": 5}, {"name": "cbCategory", "freq": 5}, {"name": "writeSampleData", "freq": 1}, {"name": "closeAboutBox", "freq": 2}, {"name": "aboutBox", "freq": 2}, {"name": "toolBarToggle", "freq": 2}, {"name": "resize", "freq": 2}]}, {"size": 4, "data": [{"name": "xSlider", "freq": 1}, {"name": "load", "freq": 1}, {"name": "btSetData", "freq": 1}, {"name": "toolTip", "freq": 1}]}, {"size": 21, "data": [{"name": "toolBarToggle", "freq": 10}, {"name": "error", "freq": 20}, {"name": "toolTip", "freq": 60}, {"name": "cbPercent", "freq": 23}, {"name": "writeSampleData", "freq": 12}, {"name": "slider", "freq": 15}, {"name": "cbCategory", "freq": 25}, {"name": "closeAboutBox", "freq": 3}, {"name": "aboutBox", "freq": 4}, {"name": "readBoundData", "freq": 22}, {"name": "warning", "freq": 8}, {"name": "setTitle", "freq": 2}, {"name": "resize", "freq": 8}, {"name": "tbBins", "freq": 6}, {"name": "pickedColor", "freq": 6}, {"name": "btColor", "freq": 8}, {"name": "bindFromPrompt", "freq": 1}, {"name": "xCbCategory", "freq": 1}, {"name": "yCbCategory", "freq": 2}, {"name": "treeStats", "freq": 2}, {"name": "writeSampleData2", "freq": 1}]}, {"size": 19, "data": [{"name": "slider", "freq": 9}, {"name": "cbPercent", "freq": 9}, {"name": "pickedColor", "freq": 6}, {"name": "btColor", "freq": 5}, {"name": "cbCategory", "freq": 7}, {"name": "toolBarToggle", "freq": 10}, {"name": "readBoundData", "freq": 8}, {"name": "resize", "freq": 2}, {"name": "appInit", "freq": 1}, {"name": "load", "freq": 1}, {"name": "error", "freq": 5}, {"name": "writeSampleData", "freq": 4}, {"name": "aboutBox", "freq": 2}, {"name": "closeErrorBox", "freq": 1}, {"name": "tbBins", "freq": 1}, {"name": "warning", "freq": 1}, {"name": "xCbCategory", "freq": 1}, {"name": "closeAboutBox", "freq": 2}, {"name": "treeStats", "freq": 2}]}, {"size": 17, "data": [{"name": "toolBarToggle", "freq": 5}, {"name": "readBoundData", "freq": 9}, {"name": "load", "freq": 8}, {"name": "appInit", "freq": 5}, {"name": "setTitle", "freq": 2}, {"name": "slider", "freq": 7}, {"name": "error", "freq": 8}, {"name": "resize", "freq": 8}, {"name": "closeAboutBox", "freq": 1}, {"name": "pickedColor", "freq": 2}, {"name": "btColor", "freq": 1}, {"name": "tbBins", "freq": 3}, {"name": "cbCategory", "freq": 2}, {"name": "cbPercent", "freq": 2}, {"name": "closeErrorBox", "freq": 1}, {"name": "writeSampleData", "freq": 2}, {"name": "setStackType", "freq": 1}]}]}, {"id": 16, "events": [{"name": "resize", "freq": 8}], "seqs": [347, 569, 605, 622, 623, 683, 724, 845], "insert": [{"size": 0, "data": []}, {"size": 0, "data": []}]}, {"id": 17, "events": [{"name": "toolTip", "freq": 5}, {"name": "readBoundData", "freq": 8}], "seqs": [23, 84, 88, 180, 350, 571, 958, 977], "insert": [{"size": 9, "data": [{"name": "toolTip", "freq": 6}, {"name": "toolBarToggle", "freq": 4}, {"name": "create", "freq": 1}, {"name": "aboutBox", "freq": 1}, {"name": "treeStats", "freq": 4}, {"name": "readBoundData", "freq": 4}, {"name": "resize", "freq": 1}, {"name": "pickedColor", "freq": 1}, {"name": "slider", "freq": 2}]}, {"size": 0, "data": []}, {"size": 2, "data": [{"name": "toolTip", "freq": 1}, {"name": "cbPercent", "freq": 1}]}]}, {"id": 18, "events": [{"name": "create", "freq": 92}, {"name": "appInit", "freq": 96}, {"name": "resize", "freq": 104}], "seqs": [27, 37, 38, 93, 108, 110, 136, 163, 168, 169, 191, 192, 193, 196, 201, 203, 211, 212, 214, 231, 244, 270, 274, 300, 308, 309, 315, 316, 317, 320, 322, 325, 328, 339, 344, 372, 384, 420, 424, 429, 436, 437, 438, 446, 447, 448, 480, 516, 528, 529, 532, 534, 538, 539, 547, 550, 551, 557, 560, 565, 567, 614, 635, 662, 663, 679, 685, 710, 717, 727, 728, 738, 746, 749, 755, 761, 763, 765, 789, 798, 799, 822, 824, 825, 827, 831, 838, 868, 880, 885, 886, 887, 890, 902, 903, 905, 912, 914, 917, 938, 967, 981, 984, 990, 994], "insert": [{"size": 16, "data": [{"name": "create", "freq": 13}, {"name": "resize", "freq": 6}, {"name": "appInit", "freq": 13}, {"name": "load", "freq": 3}, {"name": "toolBarToggle", "freq": 1}, {"name": "readBoundData", "freq": 5}, {"name": "pickedColor", "freq": 2}, {"name": "toolTip", "freq": 5}, {"name": "setStackType", "freq": 3}, {"name": "btColor", "freq": 1}, {"name": "hasColumnHeadersToggle", "freq": 2}, {"name": "closeErrorBox", "freq": 1}, {"name": "warning", "freq": 1}, {"name": "bindFromPrompt", "freq": 2}, {"name": "slider", "freq": 2}, {"name": "btSetData", "freq": 1}]}, {"size": 0, "data": []}, {"size": 13, "data": [{"name": "create", "freq": 12}, {"name": "load", "freq": 6}, {"name": "btSetData", "freq": 1}, {"name": "resize", "freq": 4}, {"name": "treeStats", "freq": 2}, {"name": "readBoundData", "freq": 1}, {"name": "bindFromPrompt", "freq": 2}, {"name": "toolBarToggle", "freq": 3}, {"name": "setTitle", "freq": 2}, {"name": "toolTip", "freq": 3}, {"name": "pickedColor", "freq": 1}, {"name": "error", "freq": 2}, {"name": "writeSampleData", "freq": 1}]}, {"size": 24, "data": [{"name": "toolBarToggle", "freq": 9}, {"name": "toolTip", "freq": 19}, {"name": "closeErrorBox", "freq": 4}, {"name": "btSetData", "freq": 8}, {"name": "readBoundData", "freq": 10}, {"name": "error", "freq": 6}, {"name": "treeStats", "freq": 11}, {"name": "appInit", "freq": 6}, {"name": "load", "freq": 1}, {"name": "bindFromPrompt", "freq": 6}, {"name": "setTitle", "freq": 2}, {"name": "writeSampleData", "freq": 1}, {"name": "warning", "freq": 1}, {"name": "setStackType", "freq": 1}, {"name": "create", "freq": 1}, {"name": "closeAboutBox", "freq": 1}, {"name": "aboutBox", "freq": 1}, {"name": "cbPercent", "freq": 1}, {"name": "cbCategory", "freq": 1}, {"name": "slider", "freq": 2}, {"name": "closeColorPicker", "freq": 4}, {"name": "pickedColor", "freq": 2}, {"name": "btColor", "freq": 3}, {"name": "xSlider", "freq": 1}]}]}, {"id": 19, "events": [{"name": "appInit", "freq": 8}, {"name": "readBoundData", "freq": 8}, {"name": "appInit", "freq": 5}], "seqs": [42, 210, 453, 470, 476, 477, 821, 835], "insert": [{"size": 3, "data": [{"name": "appInit", "freq": 3}, {"name": "toolTip", "freq": 1}, {"name": "readBoundData", "freq": 1}]}, {"size": 0, "data": []}, {"size": 0, "data": []}, {"size": 1, "data": [{"name": "readBoundData", "freq": 3}]}]}, {"id": 20, "events": [{"name": "create", "freq": 55}, {"name": "appInit", "freq": 71}, {"name": "create", "freq": 68}, {"name": "resize", "freq": 69}, {"name": "treeStats", "freq": 64}, {"name": "bindFromPrompt", "freq": 69}, {"name": "readBoundData", "freq": 70}, {"name": "treeStats", "freq": 64}, {"name": "readBoundData", "freq": 62}, {"name": "toolTip", "freq": 44}], "seqs": [26, 36, 57, 66, 73, 74, 101, 109, 114, 141, 142, 177, 233, 236, 247, 255, 256, 266, 277, 286, 351, 356, 365, 367, 368, 373, 374, 377, 383, 386, 392, 417, 430, 454, 460, 471, 472, 473, 478, 479, 503, 506, 518, 537, 580, 588, 589, 594, 613, 650, 652, 658, 676, 713, 715, 740, 744, 816, 828, 864, 865, 876, 920, 924, 935, 936, 942, 943, 964, 983, 986], "insert": [{"size": 3, "data": [{"name": "create", "freq": 8}, {"name": "resize", "freq": 5}, {"name": "treeStats", "freq": 1}]}, {"size": 0, "data": []}, {"size": 2, "data": [{"name": "resize", "freq": 3}, {"name": "create", "freq": 1}]}, {"size": 1, "data": [{"name": "appInit", "freq": 1}]}, {"size": 13, "data": [{"name": "readBoundData", "freq": 9}, {"name": "treeStats", "freq": 5}, {"name": "bindFromPrompt", "freq": 3}, {"name": "create", "freq": 1}, {"name": "btSetData", "freq": 1}, {"name": "cbCategory", "freq": 1}, {"name": "toolTip", "freq": 5}, {"name": "writeSampleData", "freq": 1}, {"name": "closeErrorBox", "freq": 2}, {"name": "warning", "freq": 2}, {"name": "error", "freq": 1}, {"name": "pickedColor", "freq": 1}, {"name": "btColor", "freq": 1}]}, {"size": 17, "data": [{"name": "toolBarToggle", "freq": 14}, {"name": "closeErrorBox", "freq": 2}, {"name": "toolTip", "freq": 31}, {"name": "error", "freq": 2}, {"name": "writeSampleData", "freq": 2}, {"name": "writeSampleData2", "freq": 5}, {"name": "resize", "freq": 16}, {"name": "readBoundData", "freq": 9}, {"name": "warning", "freq": 1}, {"name": "create", "freq": 1}, {"name": "appInit", "freq": 2}, {"name": "load", "freq": 2}, {"name": "closeAboutBox", "freq": 1}, {"name": "aboutBox", "freq": 1}, {"name": "pickedColor", "freq": 1}, {"name": "btColor", "freq": 1}, {"name": "setStackType", "freq": 1}]}, {"size": 18, "data": [{"name": "resize", "freq": 18}, {"name": "treeStats", "freq": 48}, {"name": "readBoundData", "freq": 62}, {"name": "warning", "freq": 9}, {"name": "setTitle", "freq": 5}, {"name": "toolTip", "freq": 39}, {"name": "error", "freq": 21}, {"name": "pickedColor", "freq": 16}, {"name": "closeColorPicker", "freq": 2}, {"name": "btColor", "freq": 11}, {"name": "writeSampleData2", "freq": 5}, {"name": "writeSampleData", "freq": 5}, {"name": "closeAboutBox", "freq": 3}, {"name": "aboutBox", "freq": 3}, {"name": "closeErrorBox", "freq": 13}, {"name": "load", "freq": 8}, {"name": "toolBarToggle", "freq": 9}, {"name": "appInit", "freq": 3}]}, {"size": 15, "data": [{"name": "warning", "freq": 8}, {"name": "closeErrorBox", "freq": 4}, {"name": "error", "freq": 6}, {"name": "appInit", "freq": 2}, {"name": "writeSampleData", "freq": 2}, {"name": "writeSampleData2", "freq": 2}, {"name": "toolTip", "freq": 11}, {"name": "resize", "freq": 5}, {"name": "treeStats", "freq": 2}, {"name": "closeAboutBox", "freq": 2}, {"name": "aboutBox", "freq": 2}, {"name": "cbPercent", "freq": 1}, {"name": "load", "freq": 2}, {"name": "toolBarToggle", "freq": 1}, {"name": "pickedColor", "freq": 2}]}, {"size": 17, "data": [{"name": "toolBarToggle", "freq": 7}, {"name": "toolTip", "freq": 21}, {"name": "resize", "freq": 17}, {"name": "warning", "freq": 8}, {"name": "readBoundData", "freq": 17}, {"name": "closeErrorBox", "freq": 14}, {"name": "load", "freq": 4}, {"name": "pickedColor", "freq": 8}, {"name": "btColor", "freq": 9}, {"name": "closeColorPicker", "freq": 4}, {"name": "writeSampleData", "freq": 5}, {"name": "error", "freq": 7}, {"name": "bindFromPrompt", "freq": 3}, {"name": "appInit", "freq": 7}, {"name": "setTitle", "freq": 2}, {"name": "create", "freq": 4}, {"name": "writeSampleData2", "freq": 1}]}, {"size": 19, "data": [{"name": "resize", "freq": 15}, {"name": "aboutBox", "freq": 4}, {"name": "setTitle", "freq": 3}, {"name": "error", "freq": 11}, {"name": "writeSampleData", "freq": 6}, {"name": "closeErrorBox", "freq": 9}, {"name": "pickedColor", "freq": 10}, {"name": "load", "freq": 2}, {"name": "toolBarToggle", "freq": 9}, {"name": "treeStats", "freq": 21}, {"name": "warning", "freq": 8}, {"name": "writeSampleData2", "freq": 6}, {"name": "toolTip", "freq": 24}, {"name": "closeAboutBox", "freq": 2}, {"name": "closeColorPicker", "freq": 5}, {"name": "btColor", "freq": 13}, {"name": "bindFromPrompt", "freq": 1}, {"name": "hasColumnHeadersToggle", "freq": 5}, {"name": "appInit", "freq": 1}]}, {"size": 15, "data": [{"name": "treeStats", "freq": 9}, {"name": "resize", "freq": 17}, {"name": "load", "freq": 6}, {"name": "error", "freq": 6}, {"name": "closeAboutBox", "freq": 2}, {"name": "appInit", "freq": 6}, {"name": "pickedColor", "freq": 3}, {"name": "toolBarToggle", "freq": 3}, {"name": "closeErrorBox", "freq": 4}, {"name": "warning", "freq": 7}, {"name": "readBoundData", "freq": 20}, {"name": "bindFromPrompt", "freq": 1}, {"name": "hasColumnHeadersToggle", "freq": 1}, {"name": "setTitle", "freq": 1}, {"name": "writeSampleData", "freq": 1}]}]}, {"id": 21, "events": [{"name": "create", "freq": 55}, {"name": "appInit", "freq": 64}, {"name": "create", "freq": 55}, {"name": "resize", "freq": 65}, {"name": "treeStats", "freq": 49}, {"name": "bindFromPrompt", "freq": 60}, {"name": "readBoundData", "freq": 56}, {"name": "treeStats", "freq": 52}, {"name": "readBoundData", "freq": 48}, {"name": "btColor", "freq": 57}, {"name": "pickedColor", "freq": 56}, {"name": "toolTip", "freq": 57}, {"name": "toolTip", "freq": 47}], "seqs": [11, 29, 52, 58, 69, 70, 77, 83, 103, 115, 128, 151, 178, 218, 250, 257, 288, 297, 305, 349, 358, 359, 369, 370, 380, 389, 393, 403, 405, 433, 442, 458, 459, 464, 481, 497, 498, 512, 513, 521, 525, 526, 541, 579, 609, 637, 669, 673, 682, 709, 726, 735, 742, 745, 757, 823, 873, 894, 925, 926, 934, 946, 956, 965, 978, 989], "insert": [{"size": 7, "data": [{"name": "create", "freq": 2}, {"name": "appInit", "freq": 2}, {"name": "resize", "freq": 3}, {"name": "readBoundData", "freq": 4}, {"name": "warning", "freq": 2}, {"name": "treeStats", "freq": 1}, {"name": "load", "freq": 3}]}, {"size": 0, "data": []}, {"size": 2, "data": [{"name": "resize", "freq": 4}, {"name": "load", "freq": 1}]}, {"size": 3, "data": [{"name": "treeStats", "freq": 2}, {"name": "appInit", "freq": 1}, {"name": "readBoundData", "freq": 1}]}, {"size": 18, "data": [{"name": "setTitle", "freq": 2}, {"name": "cbCategory", "freq": 1}, {"name": "toolTip", "freq": 9}, {"name": "btSetData", "freq": 5}, {"name": "toolBarToggle", "freq": 5}, {"name": "create", "freq": 2}, {"name": "appInit", "freq": 1}, {"name": "writeSampleData", "freq": 5}, {"name": "closeErrorBox", "freq": 3}, {"name": "error", "freq": 2}, {"name": "closeAboutBox", "freq": 1}, {"name": "aboutBox", "freq": 1}, {"name": "slider", "freq": 1}, {"name": "load", "freq": 1}, {"name": "warning", "freq": 1}, {"name": "treeStats", "freq": 1}, {"name": "readBoundData", "freq": 1}, {"name": "setStackType", "freq": 1}]}, {"size": 8, "data": [{"name": "resize", "freq": 7}, {"name": "toolTip", "freq": 12}, {"name": "setTitle", "freq": 1}, {"name": "readBoundData", "freq": 2}, {"name": "writeSampleData2", "freq": 1}, {"name": "warning", "freq": 2}, {"name": "aboutBox", "freq": 1}, {"name": "writeSampleData", "freq": 1}]}, {"size": 15, "data": [{"name": "closeErrorBox", "freq": 8}, {"name": "error", "freq": 7}, {"name": "warning", "freq": 9}, {"name": "readBoundData", "freq": 25}, {"name": "resize", "freq": 5}, {"name": "treeStats", "freq": 14}, {"name": "toolTip", "freq": 10}, {"name": "writeSampleData2", "freq": 1}, {"name": "toolBarToggle", "freq": 3}, {"name": "setTitle", "freq": 1}, {"name": "pickedColor", "freq": 1}, {"name": "closeColorPicker", "freq": 1}, {"name": "btColor", "freq": 1}, {"name": "writeSampleData", "freq": 1}, {"name": "hasColumnHeadersToggle", "freq": 3}]}, {"size": 19, "data": [{"name": "warning", "freq": 3}, {"name": "resize", "freq": 12}, {"name": "toolTip", "freq": 16}, {"name": "toolBarToggle", "freq": 4}, {"name": "writeSampleData2", "freq": 1}, {"name": "pickedColor", "freq": 2}, {"name": "btColor", "freq": 1}, {"name": "closeErrorBox", "freq": 4}, {"name": "closeAboutBox", "freq": 2}, {"name": "aboutBox", "freq": 2}, {"name": "slider", "freq": 6}, {"name": "treeStats", "freq": 6}, {"name": "load", "freq": 3}, {"name": "bindFromPrompt", "freq": 1}, {"name": "yCbCategory", "freq": 1}, {"name": "xCbCategory", "freq": 1}, {"name": "cbPercent", "freq": 1}, {"name": "cbCategory", "freq": 2}, {"name": "appInit", "freq": 2}]}, {"size": 12, "data": [{"name": "toolTip", "freq": 25}, {"name": "writeSampleData2", "freq": 5}, {"name": "resize", "freq": 8}, {"name": "warning", "freq": 11}, {"name": "readBoundData", "freq": 16}, {"name": "error", "freq": 11}, {"name": "pickedColor", "freq": 1}, {"name": "btColor", "freq": 1}, {"name": "closeErrorBox", "freq": 11}, {"name": "load", "freq": 2}, {"name": "toolBarToggle", "freq": 3}, {"name": "writeSampleData", "freq": 4}]}, {"size": 19, "data": [{"name": "closeAboutBox", "freq": 3}, {"name": "aboutBox", "freq": 4}, {"name": "setTitle", "freq": 2}, {"name": "toolTip", "freq": 9}, {"name": "resize", "freq": 2}, {"name": "closeErrorBox", "freq": 3}, {"name": "warning", "freq": 3}, {"name": "toolBarToggle", "freq": 4}, {"name": "treeStats", "freq": 13}, {"name": "writeSampleData", "freq": 1}, {"name": "error", "freq": 2}, {"name": "writeSampleData2", "freq": 1}, {"name": "pickedColor", "freq": 2}, {"name": "cbCategory", "freq": 2}, {"name": "cbPercent", "freq": 1}, {"name": "btSetData", "freq": 1}, {"name": "closeColorPicker", "freq": 1}, {"name": "btColor", "freq": 2}, {"name": "appInit", "freq": 1}]}, {"size": 15, "data": [{"name": "toolTip", "freq": 37}, {"name": "closeColorPicker", "freq": 4}, {"name": "pickedColor", "freq": 13}, {"name": "readBoundData", "freq": 14}, {"name": "treeStats", "freq": 13}, {"name": "resize", "freq": 6}, {"name": "closeErrorBox", "freq": 1}, {"name": "error", "freq": 6}, {"name": "writeSampleData", "freq": 2}, {"name": "closeAboutBox", "freq": 2}, {"name": "aboutBox", "freq": 2}, {"name": "toolBarToggle", "freq": 1}, {"name": "load", "freq": 1}, {"name": "appInit", "freq": 1}, {"name": "writeSampleData2", "freq": 1}]}, {"size": 25, "data": [{"name": "aboutBox", "freq": 12}, {"name": "toolTip", "freq": 40}, {"name": "writeSampleData2", "freq": 4}, {"name": "toolBarToggle", "freq": 21}, {"name": "closeColorPicker", "freq": 5}, {"name": "setTitle", "freq": 11}, {"name": "writeSampleData", "freq": 7}, {"name": "error", "freq": 13}, {"name": "closeAboutBox", "freq": 6}, {"name": "closeErrorBox", "freq": 6}, {"name": "resize", "freq": 6}, {"name": "treeStats", "freq": 12}, {"name": "readBoundData", "freq": 28}, {"name": "load", "freq": 5}, {"name": "slider", "freq": 2}, {"name": "warning", "freq": 6}, {"name": "yTbBins", "freq": 1}, {"name": "xTbBins", "freq": 1}, {"name": "xSlider", "freq": 1}, {"name": "xCbCategory", "freq": 1}, {"name": "yCbCategory", "freq": 1}, {"name": "appInit", "freq": 1}, {"name": "bindFromPrompt", "freq": 1}, {"name": "setStackType", "freq": 1}, {"name": "hasColumnHeadersToggle", "freq": 1}]}, {"size": 18, "data": [{"name": "toolBarToggle", "freq": 18}, {"name": "closeAboutBox", "freq": 10}, {"name": "error", "freq": 12}, {"name": "writeSampleData", "freq": 3}, {"name": "setTitle", "freq": 6}, {"name": "resize", "freq": 17}, {"name": "load", "freq": 12}, {"name": "readBoundData", "freq": 50}, {"name": "pickedColor", "freq": 8}, {"name": "bindFromPrompt", "freq": 2}, {"name": "closeErrorBox", "freq": 5}, {"name": "appInit", "freq": 4}, {"name": "aboutBox", "freq": 5}, {"name": "slider", "freq": 2}, {"name": "treeStats", "freq": 24}, {"name": "warning", "freq": 12}, {"name": "closeColorPicker", "freq": 3}, {"name": "hasColumnHeadersToggle", "freq": 1}]}, {"size": 17, "data": [{"name": "toolBarToggle", "freq": 7}, {"name": "treeStats", "freq": 16}, {"name": "readBoundData", "freq": 33}, {"name": "warning", "freq": 8}, {"name": "error", "freq": 8}, {"name": "setTitle", "freq": 4}, {"name": "closeErrorBox", "freq": 2}, {"name": "writeSampleData2", "freq": 2}, {"name": "resize", "freq": 12}, {"name": "load", "freq": 5}, {"name": "btSetData", "freq": 1}, {"name": "appInit", "freq": 6}, {"name": "pickedColor", "freq": 7}, {"name": "closeAboutBox", "freq": 4}, {"name": "closeColorPicker", "freq": 3}, {"name": "btColor", "freq": 1}, {"name": "aboutBox", "freq": 1}]}]}, {"id": 22, "events": [{"name": "create", "freq": 55}, {"name": "appInit", "freq": 66}, {"name": "create", "freq": 64}, {"name": "resize", "freq": 65}, {"name": "treeStats", "freq": 48}], "seqs": [5, 15, 20, 43, 100, 106, 113, 118, 131, 158, 159, 173, 217, 220, 222, 229, 252, 269, 275, 293, 294, 326, 329, 330, 348, 375, 391, 407, 412, 422, 426, 435, 440, 441, 450, 530, 563, 566, 583, 610, 618, 619, 625, 634, 648, 678, 730, 731, 737, 750, 811, 834, 843, 847, 862, 893, 911, 913, 916, 919, 921, 923, 959, 961, 985, 987, 999], "insert": [{"size": 3, "data": [{"name": "create", "freq": 6}, {"name": "resize", "freq": 4}, {"name": "appInit", "freq": 1}]}, {"size": 0, "data": []}, {"size": 4, "data": [{"name": "resize", "freq": 5}, {"name": "load", "freq": 2}, {"name": "error", "freq": 2}, {"name": "create", "freq": 1}]}, {"size": 15, "data": [{"name": "readBoundData", "freq": 4}, {"name": "error", "freq": 1}, {"name": "toolBarToggle", "freq": 3}, {"name": "toolTip", "freq": 7}, {"name": "writeSampleData", "freq": 1}, {"name": "bindFromPrompt", "freq": 2}, {"name": "setTitle", "freq": 1}, {"name": "pickedColor", "freq": 2}, {"name": "btColor", "freq": 2}, {"name": "resize", "freq": 10}, {"name": "appInit", "freq": 2}, {"name": "treeStats", "freq": 8}, {"name": "load", "freq": 1}, {"name": "closeAboutBox", "freq": 2}, {"name": "aboutBox", "freq": 2}]}, {"size": 24, "data": [{"name": "toolTip", "freq": 29}, {"name": "slider", "freq": 2}, {"name": "readBoundData", "freq": 21}, {"name": "writeSampleData", "freq": 7}, {"name": "error", "freq": 11}, {"name": "setData", "freq": 1}, {"name": "warning", "freq": 5}, {"name": "bindFromPrompt", "freq": 14}, {"name": "toolBarToggle", "freq": 5}, {"name": "closeAboutBox", "freq": 4}, {"name": "aboutBox", "freq": 4}, {"name": "setTitle", "freq": 2}, {"name": "cbPercent", "freq": 3}, {"name": "cbCategory", "freq": 4}, {"name": "treeStats", "freq": 12}, {"name": "create", "freq": 5}, {"name": "pickedColor", "freq": 3}, {"name": "btColor", "freq": 3}, {"name": "btSetData", "freq": 2}, {"name": "appInit", "freq": 3}, {"name": "load", "freq": 5}, {"name": "closeErrorBox", "freq": 4}, {"name": "writeSampleData2", "freq": 2}, {"name": "closeColorPicker", "freq": 1}]}, {"size": 20, "data": [{"name": "resize", "freq": 17}, {"name": "error", "freq": 13}, {"name": "bindFromPrompt", "freq": 2}, {"name": "closeErrorBox", "freq": 6}, {"name": "toolTip", "freq": 40}, {"name": "writeSampleData2", "freq": 4}, {"name": "closeAboutBox", "freq": 4}, {"name": "aboutBox", "freq": 4}, {"name": "setTitle", "freq": 4}, {"name": "toolBarToggle", "freq": 10}, {"name": "readBoundData", "freq": 16}, {"name": "closeColorPicker", "freq": 2}, {"name": "btColor", "freq": 6}, {"name": "writeSampleData", "freq": 3}, {"name": "warning", "freq": 3}, {"name": "appInit", "freq": 5}, {"name": "pickedColor", "freq": 6}, {"name": "setStackType", "freq": 1}, {"name": "load", "freq": 7}, {"name": "create", "freq": 1}]}]}, {"id": 23, "events": [{"name": "appInit", "freq": 64}, {"name": "create", "freq": 60}, {"name": "resize", "freq": 69}], "seqs": [12, 19, 21, 28, 67, 75, 85, 96, 97, 138, 155, 157, 176, 186, 243, 261, 276, 304, 318, 331, 341, 385, 388, 390, 408, 415, 425, 443, 449, 451, 487, 489, 500, 527, 535, 543, 546, 559, 591, 620, 628, 629, 633, 641, 651, 680, 719, 722, 748, 754, 760, 771, 780, 784, 786, 800, 856, 859, 861, 870, 878, 898, 904, 950, 968, 972, 974, 982, 998], "insert": [{"size": 11, "data": [{"name": "resize", "freq": 8}, {"name": "create", "freq": 22}, {"name": "appInit", "freq": 26}, {"name": "load", "freq": 7}, {"name": "treeStats", "freq": 3}, {"name": "error", "freq": 1}, {"name": "readBoundData", "freq": 3}, {"name": "bindFromPrompt", "freq": 1}, {"name": "btSetData", "freq": 1}, {"name": "slider", "freq": 2}, {"name": "warning", "freq": 1}]}, {"size": 0, "data": []}, {"size": 18, "data": [{"name": "treeStats", "freq": 6}, {"name": "resize", "freq": 18}, {"name": "load", "freq": 7}, {"name": "readBoundData", "freq": 5}, {"name": "appInit", "freq": 3}, {"name": "toolTip", "freq": 14}, {"name": "pickedColor", "freq": 1}, {"name": "btSetData", "freq": 1}, {"name": "setTitle", "freq": 1}, {"name": "writeSampleData", "freq": 3}, {"name": "closeColorPicker", "freq": 1}, {"name": "yCbCategory", "freq": 1}, {"name": "xCbCategory", "freq": 1}, {"name": "closeErrorBox", "freq": 2}, {"name": "error", "freq": 5}, {"name": "toolBarToggle", "freq": 2}, {"name": "cbCategory", "freq": 1}, {"name": "cbPercent", "freq": 1}]}, {"size": 27, "data": [{"name": "toolTip", "freq": 33}, {"name": "toolBarToggle", "freq": 11}, {"name": "btSetData", "freq": 8}, {"name": "closeAboutBox", "freq": 1}, {"name": "aboutBox", "freq": 1}, {"name": "cbPercent", "freq": 5}, {"name": "cbCategory", "freq": 2}, {"name": "treeStats", "freq": 22}, {"name": "create", "freq": 2}, {"name": "slider", "freq": 2}, {"name": "writeSampleData", "freq": 8}, {"name": "readBoundData", "freq": 20}, {"name": "closeErrorBox", "freq": 5}, {"name": "error", "freq": 9}, {"name": "bindFromPrompt", "freq": 11}, {"name": "appInit", "freq": 5}, {"name": "writeSampleData2", "freq": 3}, {"name": "ySlider", "freq": 1}, {"name": "xSlider", "freq": 2}, {"name": "pickedColor", "freq": 1}, {"name": "btColor", "freq": 1}, {"name": "warning", "freq": 1}, {"name": "yCbCategory", "freq": 2}, {"name": "xCbCategory", "freq": 3}, {"name": "setTitle", "freq": 1}, {"name": "tbBins", "freq": 1}, {"name": "setStackType", "freq": 1}]}]}, {"id": 24, "events": [{"name": "load", "freq": 15}, {"name": "appInit", "freq": 19}, {"name": "load", "freq": 20}, {"name": "readBoundData", "freq": 22}, {"name": "load", "freq": 18}, {"name": "resize", "freq": 22}, {"name": "readBoundData", "freq": 22}, {"name": "resize", "freq": 19}, {"name": "readBoundData", "freq": 19}, {"name": "resize", "freq": 20}], "seqs": [34, 78, 99, 124, 207, 333, 346, 406, 552, 626, 631, 675, 694, 696, 697, 698, 702, 706, 707, 712, 768, 891, 980], "insert": [{"size": 20, "data": [{"name": "create", "freq": 6}, {"name": "load", "freq": 28}, {"name": "warning", "freq": 4}, {"name": "treeStats", "freq": 10}, {"name": "readBoundData", "freq": 23}, {"name": "resize", "freq": 27}, {"name": "appInit", "freq": 15}, {"name": "setStackType", "freq": 5}, {"name": "toolTip", "freq": 6}, {"name": "closeErrorBox", "freq": 2}, {"name": "toolBarToggle", "freq": 4}, {"name": "setTitle", "freq": 4}, {"name": "pickedColor", "freq": 1}, {"name": "btColor", "freq": 1}, {"name": "tbBins", "freq": 1}, {"name": "bindFromPrompt", "freq": 2}, {"name": "btSetData", "freq": 1}, {"name": "error", "freq": 1}, {"name": "writeSampleData", "freq": 1}, {"name": "writeSampleData2", "freq": 1}]}, {"size": 0, "data": []}, {"size": 7, "data": [{"name": "readBoundData", "freq": 4}, {"name": "resize", "freq": 4}, {"name": "treeStats", "freq": 2}, {"name": "bindFromPrompt", "freq": 1}, {"name": "closeAboutBox", "freq": 1}, {"name": "toolTip", "freq": 1}, {"name": "aboutBox", "freq": 1}]}, {"size": 6, "data": [{"name": "resize", "freq": 11}, {"name": "warning", "freq": 1}, {"name": "appInit", "freq": 2}, {"name": "setStackType", "freq": 2}, {"name": "treeStats", "freq": 4}, {"name": "readBoundData", "freq": 2}]}, {"size": 7, "data": [{"name": "create", "freq": 1}, {"name": "load", "freq": 2}, {"name": "appInit", "freq": 7}, {"name": "treeStats", "freq": 4}, {"name": "warning", "freq": 1}, {"name": "resize", "freq": 5}, {"name": "bindFromPrompt", "freq": 1}]}, {"size": 5, "data": [{"name": "treeStats", "freq": 3}, {"name": "warning", "freq": 1}, {"name": "readBoundData", "freq": 2}, {"name": "appInit", "freq": 3}, {"name": "resize", "freq": 1}]}, {"size": 11, "data": [{"name": "treeStats", "freq": 9}, {"name": "load", "freq": 2}, {"name": "appInit", "freq": 4}, {"name": "warning", "freq": 3}, {"name": "readBoundData", "freq": 4}, {"name": "setStackType", "freq": 2}, {"name": "bindFromPrompt", "freq": 3}, {"name": "toolTip", "freq": 4}, {"name": "writeSampleData", "freq": 1}, {"name": "error", "freq": 1}, {"name": "writeSampleData2", "freq": 1}]}, {"size": 13, "data": [{"name": "treeStats", "freq": 12}, {"name": "create", "freq": 1}, {"name": "load", "freq": 10}, {"name": "appInit", "freq": 11}, {"name": "resize", "freq": 4}, {"name": "warning", "freq": 2}, {"name": "closeErrorBox", "freq": 1}, {"name": "toolTip", "freq": 4}, {"name": "error", "freq": 1}, {"name": "writeSampleData2", "freq": 1}, {"name": "bindFromPrompt", "freq": 1}, {"name": "pickedColor", "freq": 1}, {"name": "btColor", "freq": 1}]}, {"size": 5, "data": [{"name": "appInit", "freq": 1}, {"name": "toolTip", "freq": 2}, {"name": "toolBarToggle", "freq": 1}, {"name": "setStackType", "freq": 2}, {"name": "bindFromPrompt", "freq": 6}]}, {"size": 6, "data": [{"name": "warning", "freq": 1}, {"name": "appInit", "freq": 3}, {"name": "load", "freq": 3}, {"name": "setTitle", "freq": 1}, {"name": "treeStats", "freq": 6}, {"name": "resize", "freq": 1}]}, {"size": 8, "data": [{"name": "treeStats", "freq": 3}, {"name": "warning", "freq": 2}, {"name": "readBoundData", "freq": 6}, {"name": "appInit", "freq": 2}, {"name": "toolTip", "freq": 4}, {"name": "setStackType", "freq": 1}, {"name": "pickedColor", "freq": 1}, {"name": "load", "freq": 1}]}]}, {"id": 25, "events": [{"name": "load", "freq": 81}, {"name": "appInit", "freq": 132}, {"name": "load", "freq": 96}, {"name": "resize", "freq": 144}, {"name": "readBoundData", "freq": 113}], "seqs": [22, 25, 31, 35, 44, 45, 60, 64, 117, 123, 130, 144, 148, 150, 156, 160, 161, 165, 167, 170, 171, 172, 200, 202, 204, 205, 206, 213, 232, 248, 251, 260, 273, 282, 299, 302, 327, 332, 334, 335, 336, 340, 342, 343, 345, 352, 353, 355, 379, 395, 396, 400, 409, 414, 416, 423, 434, 462, 463, 469, 484, 493, 502, 505, 507, 508, 514, 517, 531, 540, 549, 561, 562, 598, 600, 601, 602, 603, 604, 608, 612, 615, 624, 627, 644, 654, 659, 660, 671, 672, 684, 693, 695, 699, 700, 701, 703, 704, 705, 718, 720, 725, 736, 743, 751, 752, 753, 758, 759, 764, 770, 774, 777, 779, 782, 785, 787, 788, 796, 797, 805, 806, 813, 815, 826, 833, 837, 840, 841, 855, 857, 858, 863, 869, 882, 883, 888, 889, 892, 896, 897, 915, 922, 948, 949, 954, 955, 962, 963, 969, 970, 973, 988], "insert": [{"size": 22, "data": [{"name": "readBoundData", "freq": 54}, {"name": "load", "freq": 82}, {"name": "appInit", "freq": 62}, {"name": "resize", "freq": 86}, {"name": "create", "freq": 19}, {"name": "error", "freq": 9}, {"name": "cbPercent", "freq": 5}, {"name": "toolTip", "freq": 26}, {"name": "cbCategory", "freq": 4}, {"name": "writeSampleData", "freq": 2}, {"name": "closeErrorBox", "freq": 4}, {"name": "bindFromPrompt", "freq": 7}, {"name": "btSetData", "freq": 7}, {"name": "toolBarToggle", "freq": 11}, {"name": "setStackType", "freq": 3}, {"name": "treeStats", "freq": 12}, {"name": "warning", "freq": 7}, {"name": "pickedColor", "freq": 6}, {"name": "slider", "freq": 3}, {"name": "setTitle", "freq": 8}, {"name": "btColor", "freq": 4}, {"name": "tbBins", "freq": 7}]}, {"size": 0, "data": []}, {"size": 20, "data": [{"name": "resize", "freq": 30}, {"name": "readBoundData", "freq": 34}, {"name": "load", "freq": 12}, {"name": "create", "freq": 16}, {"name": "btSetData", "freq": 3}, {"name": "toolBarToggle", "freq": 6}, {"name": "toolTip", "freq": 14}, {"name": "error", "freq": 5}, {"name": "treeStats", "freq": 14}, {"name": "pickedColor", "freq": 6}, {"name": "btColor", "freq": 4}, {"name": "tbBins", "freq": 1}, {"name": "warning", "freq": 3}, {"name": "aboutBox", "freq": 2}, {"name": "bindFromPrompt", "freq": 4}, {"name": "setTitle", "freq": 3}, {"name": "closeErrorBox", "freq": 2}, {"name": "slider", "freq": 1}, {"name": "closeAboutBox", "freq": 1}, {"name": "setStackType", "freq": 1}]}, {"size": 13, "data": [{"name": "appInit", "freq": 9}, {"name": "readBoundData", "freq": 20}, {"name": "resize", "freq": 15}, {"name": "create", "freq": 4}, {"name": "treeStats", "freq": 14}, {"name": "bindFromPrompt", "freq": 2}, {"name": "pickedColor", "freq": 3}, {"name": "closeColorPicker", "freq": 3}, {"name": "toolTip", "freq": 13}, {"name": "btColor", "freq": 2}, {"name": "toolBarToggle", "freq": 4}, {"name": "setTitle", "freq": 3}, {"name": "tbBins", "freq": 1}]}, {"size": 26, "data": [{"name": "closeErrorBox", "freq": 7}, {"name": "error", "freq": 10}, {"name": "bindFromPrompt", "freq": 23}, {"name": "toolTip", "freq": 25}, {"name": "readBoundData", "freq": 40}, {"name": "warning", "freq": 14}, {"name": "closeAboutBox", "freq": 3}, {"name": "aboutBox", "freq": 3}, {"name": "treeStats", "freq": 29}, {"name": "appInit", "freq": 13}, {"name": "xTbBins", "freq": 3}, {"name": "pickedColor", "freq": 3}, {"name": "btColor", "freq": 1}, {"name": "yTbBins", "freq": 1}, {"name": "writeSampleData", "freq": 3}, {"name": "btSetData", "freq": 5}, {"name": "cbCategory", "freq": 3}, {"name": "toolBarToggle", "freq": 8}, {"name": "load", "freq": 4}, {"name": "writeSampleData2", "freq": 1}, {"name": "cbPercent", "freq": 1}, {"name": "setStackType", "freq": 8}, {"name": "create", "freq": 1}, {"name": "setTitle", "freq": 1}, {"name": "hasColumnHeadersToggle", "freq": 1}, {"name": "slider", "freq": 1}]}, {"size": 26, "data": [{"name": "load", "freq": 8}, {"name": "resize", "freq": 34}, {"name": "treeStats", "freq": 19}, {"name": "pickedColor", "freq": 8}, {"name": "toolTip", "freq": 29}, {"name": "closeColorPicker", "freq": 3}, {"name": "btColor", "freq": 7}, {"name": "closeErrorBox", "freq": 3}, {"name": "error", "freq": 3}, {"name": "writeSampleData", "freq": 2}, {"name": "appInit", "freq": 18}, {"name": "toolBarToggle", "freq": 10}, {"name": "yTbBins", "freq": 1}, {"name": "warning", "freq": 8}, {"name": "create", "freq": 7}, {"name": "closeAboutBox", "freq": 1}, {"name": "aboutBox", "freq": 1}, {"name": "cbPercent", "freq": 4}, {"name": "cbCategory", "freq": 3}, {"name": "slider", "freq": 2}, {"name": "ySlider", "freq": 3}, {"name": "setTitle", "freq": 2}, {"name": "xTbBins", "freq": 1}, {"name": "xSlider", "freq": 1}, {"name": "hasColumnHeadersToggle", "freq": 1}, {"name": "bindFromPrompt", "freq": 1}]}]}, {"id": 26, "events": [{"name": "appInit", "freq": 62}, {"name": "create", "freq": 58}, {"name": "resize", "freq": 64}, {"name": "bindFromPrompt", "freq": 58}, {"name": "readBoundData", "freq": 54}, {"name": "toolTip", "freq": 51}, {"name": "toolTip", "freq": 51}], "seqs": [9, 14, 16, 17, 32, 39, 46, 47, 86, 87, 89, 102, 107, 121, 132, 135, 153, 154, 162, 164, 194, 195, 199, 221, 238, 239, 240, 246, 263, 280, 281, 284, 295, 363, 398, 401, 411, 413, 455, 461, 474, 488, 519, 568, 570, 573, 611, 616, 621, 630, 643, 649, 691, 692, 756, 775, 790, 793, 807, 829, 832, 848, 849, 850, 852, 866, 872, 879, 895, 906, 996], "insert": [{"size": 10, "data": [{"name": "appInit", "freq": 31}, {"name": "create", "freq": 23}, {"name": "resize", "freq": 15}, {"name": "error", "freq": 1}, {"name": "closeAboutBox", "freq": 1}, {"name": "treeStats", "freq": 2}, {"name": "load", "freq": 1}, {"name": "readBoundData", "freq": 1}, {"name": "toolTip", "freq": 1}, {"name": "btColor", "freq": 1}]}, {"size": 0, "data": []}, {"size": 16, "data": [{"name": "error", "freq": 3}, {"name": "toolTip", "freq": 7}, {"name": "toolBarToggle", "freq": 2}, {"name": "resize", "freq": 13}, {"name": "appInit", "freq": 3}, {"name": "readBoundData", "freq": 6}, {"name": "load", "freq": 1}, {"name": "treeStats", "freq": 7}, {"name": "pickedColor", "freq": 1}, {"name": "btColor", "freq": 1}, {"name": "closeErrorBox", "freq": 2}, {"name": "bindFromPrompt", "freq": 1}, {"name": "closeAboutBox", "freq": 1}, {"name": "aboutBox", "freq": 1}, {"name": "writeSampleData", "freq": 2}, {"name": "btSetData", "freq": 2}]}, {"size": 21, "data": [{"name": "toolTip", "freq": 50}, {"name": "setTitle", "freq": 8}, {"name": "writeSampleData", "freq": 11}, {"name": "toolBarToggle", "freq": 22}, {"name": "btSetData", "freq": 17}, {"name": "pickedColor", "freq": 8}, {"name": "btColor", "freq": 9}, {"name": "aboutBox", "freq": 2}, {"name": "cbPercent", "freq": 2}, {"name": "closeErrorBox", "freq": 7}, {"name": "error", "freq": 6}, {"name": "slider", "freq": 1}, {"name": "appInit", "freq": 3}, {"name": "writeSampleData2", "freq": 1}, {"name": "closeColorPicker", "freq": 4}, {"name": "treeStats", "freq": 8}, {"name": "cbCategory", "freq": 2}, {"name": "closeAboutBox", "freq": 1}, {"name": "create", "freq": 3}, {"name": "readBoundData", "freq": 3}, {"name": "warning", "freq": 1}]}, {"size": 25, "data": [{"name": "aboutBox", "freq": 3}, {"name": "toolTip", "freq": 29}, {"name": "writeSampleData", "freq": 7}, {"name": "warning", "freq": 15}, {"name": "readBoundData", "freq": 34}, {"name": "closeErrorBox", "freq": 23}, {"name": "error", "freq": 28}, {"name": "pickedColor", "freq": 10}, {"name": "slider", "freq": 4}, {"name": "cbPercent", "freq": 4}, {"name": "btColor", "freq": 8}, {"name": "setTitle", "freq": 2}, {"name": "cbCategory", "freq": 5}, {"name": "closeAboutBox", "freq": 2}, {"name": "resize", "freq": 4}, {"name": "treeStats", "freq": 12}, {"name": "hasColumnHeadersToggle", "freq": 4}, {"name": "load", "freq": 2}, {"name": "appInit", "freq": 1}, {"name": "xCbCategory", "freq": 2}, {"name": "ySlider", "freq": 1}, {"name": "xSlider", "freq": 1}, {"name": "toolBarToggle", "freq": 4}, {"name": "tbBins", "freq": 1}, {"name": "closeColorPicker", "freq": 1}]}, {"size": 25, "data": [{"name": "error", "freq": 14}, {"name": "writeSampleData", "freq": 8}, {"name": "closeErrorBox", "freq": 18}, {"name": "pickedColor", "freq": 14}, {"name": "slider", "freq": 5}, {"name": "cbCategory", "freq": 3}, {"name": "toolTip", "freq": 24}, {"name": "btColor", "freq": 13}, {"name": "treeStats", "freq": 6}, {"name": "resize", "freq": 8}, {"name": "warning", "freq": 3}, {"name": "closeAboutBox", "freq": 5}, {"name": "aboutBox", "freq": 5}, {"name": "xSlider", "freq": 1}, {"name": "ySlider", "freq": 1}, {"name": "xTbBins", "freq": 1}, {"name": "load", "freq": 1}, {"name": "toolBarToggle", "freq": 5}, {"name": "writeSampleData2", "freq": 1}, {"name": "hasColumnHeadersToggle", "freq": 3}, {"name": "setTitle", "freq": 2}, {"name": "tbBins", "freq": 1}, {"name": "closeColorPicker", "freq": 1}, {"name": "cbPercent", "freq": 1}, {"name": "btSetData", "freq": 1}]}, {"size": 28, "data": [{"name": "btColor", "freq": 9}, {"name": "closeAboutBox", "freq": 2}, {"name": "pickedColor", "freq": 12}, {"name": "aboutBox", "freq": 3}, {"name": "readBoundData", "freq": 21}, {"name": "error", "freq": 12}, {"name": "slider", "freq": 4}, {"name": "warning", "freq": 1}, {"name": "closeErrorBox", "freq": 4}, {"name": "cbCategory", "freq": 5}, {"name": "load", "freq": 7}, {"name": "appInit", "freq": 4}, {"name": "resize", "freq": 10}, {"name": "cbPercent", "freq": 3}, {"name": "setTitle", "freq": 3}, {"name": "writeSampleData", "freq": 4}, {"name": "writeSampleData2", "freq": 2}, {"name": "yTbBins", "freq": 1}, {"name": "toolBarToggle", "freq": 6}, {"name": "hasColumnHeadersToggle", "freq": 3}, {"name": "btSetData", "freq": 1}, {"name": "create", "freq": 1}, {"name": "bindFromPrompt", "freq": 1}, {"name": "closeColorPicker", "freq": 1}, {"name": "xCbCategory", "freq": 1}, {"name": "yCbCategory", "freq": 1}, {"name": "ySlider", "freq": 1}, {"name": "xSlider", "freq": 1}]}, {"size": 18, "data": [{"name": "readBoundData", "freq": 25}, {"name": "pickedColor", "freq": 10}, {"name": "load", "freq": 9}, {"name": "appInit", "freq": 10}, {"name": "closeErrorBox", "freq": 5}, {"name": "error", "freq": 10}, {"name": "btColor", "freq": 2}, {"name": "closeAboutBox", "freq": 3}, {"name": "resize", "freq": 15}, {"name": "cbPercent", "freq": 3}, {"name": "slider", "freq": 3}, {"name": "toolBarToggle", "freq": 3}, {"name": "bindFromPrompt", "freq": 1}, {"name": "create", "freq": 4}, {"name": "treeStats", "freq": 4}, {"name": "warning", "freq": 1}, {"name": "closeColorPicker", "freq": 1}, {"name": "setTitle", "freq": 2}]}]}, {"id": 27, "events": [{"name": "create", "freq": 101}, {"name": "appInit", "freq": 99}, {"name": "resize", "freq": 106}, {"name": "toolTip", "freq": 84}, {"name": "toolTip", "freq": 67}], "seqs": [0, 1, 3, 7, 8, 10, 18, 40, 41, 49, 50, 54, 55, 62, 82, 91, 95, 105, 129, 134, 146, 183, 189, 190, 216, 223, 225, 234, 241, 249, 253, 258, 267, 268, 271, 283, 289, 290, 291, 306, 307, 310, 311, 312, 321, 366, 381, 382, 397, 399, 402, 410, 428, 432, 439, 444, 445, 452, 467, 511, 520, 533, 536, 542, 545, 554, 617, 632, 636, 639, 640, 642, 645, 647, 657, 668, 670, 690, 708, 714, 729, 739, 747, 762, 791, 801, 802, 809, 810, 818, 819, 830, 842, 853, 854, 860, 867, 871, 881, 884, 899, 931, 941, 951, 952, 953, 976, 991, 995], "insert": [{"size": 17, "data": [{"name": "create", "freq": 22}, {"name": "resize", "freq": 15}, {"name": "appInit", "freq": 12}, {"name": "readBoundData", "freq": 1}, {"name": "treeStats", "freq": 2}, {"name": "load", "freq": 1}, {"name": "toolTip", "freq": 9}, {"name": "closeAboutBox", "freq": 1}, {"name": "aboutBox", "freq": 1}, {"name": "setTitle", "freq": 1}, {"name": "pickedColor", "freq": 1}, {"name": "btColor", "freq": 1}, {"name": "tbBins", "freq": 3}, {"name": "slider", "freq": 1}, {"name": "error", "freq": 1}, {"name": "bindFromPrompt", "freq": 1}, {"name": "btSetData", "freq": 1}]}, {"size": 0, "data": []}, {"size": 24, "data": [{"name": "toolTip", "freq": 28}, {"name": "toolBarToggle", "freq": 5}, {"name": "resize", "freq": 23}, {"name": "create", "freq": 27}, {"name": "cbPercent", "freq": 4}, {"name": "pickedColor", "freq": 5}, {"name": "btColor", "freq": 5}, {"name": "closeErrorBox", "freq": 5}, {"name": "error", "freq": 9}, {"name": "writeSampleData", "freq": 3}, {"name": "treeStats", "freq": 27}, {"name": "readBoundData", "freq": 26}, {"name": "bindFromPrompt", "freq": 8}, {"name": "yTbBins", "freq": 2}, {"name": "xTbBins", "freq": 2}, {"name": "load", "freq": 2}, {"name": "btSetData", "freq": 5}, {"name": "warning", "freq": 2}, {"name": "cbCategory", "freq": 3}, {"name": "closeColorPicker", "freq": 1}, {"name": "setStackType", "freq": 1}, {"name": "closeAboutBox", "freq": 1}, {"name": "aboutBox", "freq": 1}, {"name": "slider", "freq": 1}]}, {"size": 27, "data": [{"name": "toolBarToggle", "freq": 49}, {"name": "error", "freq": 32}, {"name": "setData", "freq": 1}, {"name": "writeSampleData", "freq": 21}, {"name": "toolTip", "freq": 57}, {"name": "create", "freq": 2}, {"name": "treeStats", "freq": 30}, {"name": "writeSampleData2", "freq": 5}, {"name": "closeColorPicker", "freq": 1}, {"name": "btColor", "freq": 13}, {"name": "btSetData", "freq": 8}, {"name": "closeAboutBox", "freq": 3}, {"name": "aboutBox", "freq": 8}, {"name": "cbCategory", "freq": 7}, {"name": "closeErrorBox", "freq": 16}, {"name": "setTitle", "freq": 3}, {"name": "pickedColor", "freq": 9}, {"name": "slider", "freq": 7}, {"name": "bindFromPrompt", "freq": 15}, {"name": "readBoundData", "freq": 28}, {"name": "appInit", "freq": 4}, {"name": "warning", "freq": 6}, {"name": "tbBins", "freq": 3}, {"name": "yTbBins", "freq": 1}, {"name": "xTbBins", "freq": 1}, {"name": "cbPercent", "freq": 3}, {"name": "hasColumnHeadersToggle", "freq": 1}]}, {"size": 29, "data": [{"name": "toolBarToggle", "freq": 40}, {"name": "error", "freq": 16}, {"name": "setData", "freq": 1}, {"name": "closeColorPicker", "freq": 4}, {"name": "btColor", "freq": 5}, {"name": "closeErrorBox", "freq": 14}, {"name": "resize", "freq": 29}, {"name": "treeStats", "freq": 6}, {"name": "readBoundData", "freq": 23}, {"name": "bindFromPrompt", "freq": 9}, {"name": "cbPercent", "freq": 3}, {"name": "appInit", "freq": 13}, {"name": "load", "freq": 10}, {"name": "btSetData", "freq": 4}, {"name": "writeSampleData", "freq": 4}, {"name": "pickedColor", "freq": 7}, {"name": "setTitle", "freq": 5}, {"name": "aboutBox", "freq": 4}, {"name": "closeAboutBox", "freq": 7}, {"name": "cbCategory", "freq": 1}, {"name": "warning", "freq": 5}, {"name": "hasColumnHeadersToggle", "freq": 1}, {"name": "slider", "freq": 3}, {"name": "yCbCategory", "freq": 1}, {"name": "xCbCategory", "freq": 1}, {"name": "create", "freq": 4}, {"name": "ySlider", "freq": 1}, {"name": "xSlider", "freq": 1}, {"name": "tbBins", "freq": 2}]}, {"size": 20, "data": [{"name": "toolBarToggle", "freq": 9}, {"name": "closeAboutBox", "freq": 6}, {"name": "aboutBox", "freq": 5}, {"name": "pickedColor", "freq": 6}, {"name": "btColor", "freq": 2}, {"name": "closeErrorBox", "freq": 5}, {"name": "resize", "freq": 13}, {"name": "error", "freq": 9}, {"name": "cbCategory", "freq": 1}, {"name": "closeColorPicker", "freq": 2}, {"name": "readBoundData", "freq": 7}, {"name": "treeStats", "freq": 3}, {"name": "bindFromPrompt", "freq": 5}, {"name": "btSetData", "freq": 2}, {"name": "appInit", "freq": 8}, {"name": "load", "freq": 3}, {"name": "create", "freq": 2}, {"name": "hasColumnHeadersToggle", "freq": 1}, {"name": "setTitle", "freq": 1}, {"name": "tbBins", "freq": 2}]}]}, {"id": 28, "events": [{"name": "create", "freq": 63}, {"name": "appInit", "freq": 66}, {"name": "resize", "freq": 69}, {"name": "toolTip", "freq": 51}, {"name": "bindFromPrompt", "freq": 61}, {"name": "readBoundData", "freq": 58}, {"name": "toolTip", "freq": 68}, {"name": "toolTip", "freq": 56}, {"name": "toolTip", "freq": 50}], "seqs": [4, 6, 13, 33, 48, 51, 53, 56, 65, 80, 94, 122, 147, 166, 175, 185, 208, 209, 226, 227, 228, 235, 237, 242, 245, 287, 303, 313, 314, 319, 357, 364, 418, 419, 421, 427, 431, 482, 490, 492, 556, 592, 596, 597, 599, 653, 664, 665, 666, 667, 674, 769, 772, 776, 778, 781, 795, 808, 812, 814, 817, 875, 877, 900, 901, 909, 918, 930, 947, 960, 993], "insert": [{"size": 4, "data": [{"name": "create", "freq": 12}, {"name": "resize", "freq": 7}, {"name": "appInit", "freq": 7}, {"name": "toolTip", "freq": 1}]}, {"size": 0, "data": []}, {"size": 19, "data": [{"name": "create", "freq": 10}, {"name": "toolBarToggle", "freq": 3}, {"name": "toolTip", "freq": 12}, {"name": "resize", "freq": 10}, {"name": "readBoundData", "freq": 10}, {"name": "load", "freq": 1}, {"name": "treeStats", "freq": 6}, {"name": "pickedColor", "freq": 4}, {"name": "btColor", "freq": 4}, {"name": "bindFromPrompt", "freq": 4}, {"name": "cbCategory", "freq": 2}, {"name": "cbPercent", "freq": 3}, {"name": "setTitle", "freq": 2}, {"name": "writeSampleData2", "freq": 1}, {"name": "error", "freq": 2}, {"name": "writeSampleData", "freq": 1}, {"name": "tbBins", "freq": 1}, {"name": "slider", "freq": 3}, {"name": "btSetData", "freq": 1}]}, {"size": 24, "data": [{"name": "error", "freq": 17}, {"name": "toolTip", "freq": 52}, {"name": "setData", "freq": 1}, {"name": "toolBarToggle", "freq": 12}, {"name": "setTitle", "freq": 6}, {"name": "writeSampleData", "freq": 19}, {"name": "create", "freq": 4}, {"name": "closeAboutBox", "freq": 4}, {"name": "aboutBox", "freq": 5}, {"name": "btSetData", "freq": 18}, {"name": "pickedColor", "freq": 11}, {"name": "closeColorPicker", "freq": 3}, {"name": "btColor", "freq": 13}, {"name": "closeErrorBox", "freq": 10}, {"name": "appInit", "freq": 3}, {"name": "cbCategory", "freq": 12}, {"name": "slider", "freq": 11}, {"name": "readBoundData", "freq": 11}, {"name": "bindFromPrompt", "freq": 4}, {"name": "treeStats", "freq": 8}, {"name": "load", "freq": 2}, {"name": "cbPercent", "freq": 8}, {"name": "warning", "freq": 1}, {"name": "tbBins", "freq": 1}]}, {"size": 21, "data": [{"name": "slider", "freq": 3}, {"name": "error", "freq": 5}, {"name": "closeErrorBox", "freq": 6}, {"name": "writeSampleData", "freq": 4}, {"name": "toolBarToggle", "freq": 3}, {"name": "closeAboutBox", "freq": 3}, {"name": "btSetData", "freq": 17}, {"name": "readBoundData", "freq": 9}, {"name": "warning", "freq": 3}, {"name": "bindFromPrompt", "freq": 2}, {"name": "cbCategory", "freq": 5}, {"name": "cbPercent", "freq": 3}, {"name": "resize", "freq": 10}, {"name": "treeStats", "freq": 6}, {"name": "setTitle", "freq": 5}, {"name": "pickedColor", "freq": 3}, {"name": "btColor", "freq": 2}, {"name": "appInit", "freq": 6}, {"name": "load", "freq": 5}, {"name": "writeSampleData2", "freq": 1}, {"name": "aboutBox", "freq": 2}]}, {"size": 22, "data": [{"name": "error", "freq": 23}, {"name": "writeSampleData", "freq": 5}, {"name": "readBoundData", "freq": 26}, {"name": "closeErrorBox", "freq": 15}, {"name": "warning", "freq": 8}, {"name": "toolTip", "freq": 38}, {"name": "pickedColor", "freq": 9}, {"name": "btColor", "freq": 7}, {"name": "slider", "freq": 4}, {"name": "cbPercent", "freq": 3}, {"name": "cbCategory", "freq": 1}, {"name": "resize", "freq": 4}, {"name": "load", "freq": 3}, {"name": "appInit", "freq": 1}, {"name": "treeStats", "freq": 5}, {"name": "setTitle", "freq": 2}, {"name": "aboutBox", "freq": 3}, {"name": "toolBarToggle", "freq": 6}, {"name": "closeAboutBox", "freq": 2}, {"name": "hasColumnHeadersToggle", "freq": 4}, {"name": "setStackType", "freq": 1}, {"name": "closeColorPicker", "freq": 1}]}, {"size": 28, "data": [{"name": "cbPercent", "freq": 6}, {"name": "pickedColor", "freq": 15}, {"name": "toolTip", "freq": 34}, {"name": "btColor", "freq": 14}, {"name": "load", "freq": 4}, {"name": "appInit", "freq": 2}, {"name": "cbCategory", "freq": 5}, {"name": "resize", "freq": 17}, {"name": "yCbCategory", "freq": 3}, {"name": "ySlider", "freq": 2}, {"name": "toolBarToggle", "freq": 8}, {"name": "slider", "freq": 8}, {"name": "xCbCategory", "freq": 2}, {"name": "yTbBins", "freq": 1}, {"name": "xTbBins", "freq": 1}, {"name": "closeErrorBox", "freq": 5}, {"name": "error", "freq": 8}, {"name": "aboutBox", "freq": 5}, {"name": "writeSampleData", "freq": 3}, {"name": "closeAboutBox", "freq": 1}, {"name": "setTitle", "freq": 8}, {"name": "tbBins", "freq": 5}, {"name": "closeColorPicker", "freq": 2}, {"name": "treeStats", "freq": 8}, {"name": "writeSampleData2", "freq": 4}, {"name": "xSlider", "freq": 1}, {"name": "warning", "freq": 2}, {"name": "setStackType", "freq": 1}]}, {"size": 24, "data": [{"name": "writeSampleData", "freq": 4}, {"name": "error", "freq": 16}, {"name": "setData", "freq": 1}, {"name": "cbCategory", "freq": 9}, {"name": "cbPercent", "freq": 5}, {"name": "toolBarToggle", "freq": 17}, {"name": "aboutBox", "freq": 8}, {"name": "ySlider", "freq": 3}, {"name": "pickedColor", "freq": 12}, {"name": "yTbBins", "freq": 1}, {"name": "closeErrorBox", "freq": 10}, {"name": "readBoundData", "freq": 17}, {"name": "btColor", "freq": 6}, {"name": "setTitle", "freq": 8}, {"name": "resize", "freq": 12}, {"name": "appInit", "freq": 6}, {"name": "warning", "freq": 5}, {"name": "closeAboutBox", "freq": 7}, {"name": "load", "freq": 10}, {"name": "tbBins", "freq": 2}, {"name": "treeStats", "freq": 3}, {"name": "bindFromPrompt", "freq": 3}, {"name": "slider", "freq": 5}, {"name": "writeSampleData2", "freq": 1}]}, {"size": 27, "data": [{"name": "toolBarToggle", "freq": 23}, {"name": "load", "freq": 13}, {"name": "pickedColor", "freq": 11}, {"name": "btColor", "freq": 5}, {"name": "cbCategory", "freq": 6}, {"name": "readBoundData", "freq": 20}, {"name": "closeAboutBox", "freq": 6}, {"name": "yTbBins", "freq": 2}, {"name": "ySlider", "freq": 2}, {"name": "yCbCategory", "freq": 2}, {"name": "xTbBins", "freq": 1}, {"name": "error", "freq": 10}, {"name": "aboutBox", "freq": 1}, {"name": "cbPercent", "freq": 5}, {"name": "closeErrorBox", "freq": 5}, {"name": "treeStats", "freq": 6}, {"name": "warning", "freq": 3}, {"name": "bindFromPrompt", "freq": 2}, {"name": "resize", "freq": 16}, {"name": "writeSampleData", "freq": 7}, {"name": "closeColorPicker", "freq": 2}, {"name": "btSetData", "freq": 1}, {"name": "slider", "freq": 1}, {"name": "appInit", "freq": 8}, {"name": "xSlider", "freq": 1}, {"name": "setTitle", "freq": 2}, {"name": "writeSampleData2", "freq": 1}]}, {"size": 16, "data": [{"name": "readBoundData", "freq": 16}, {"name": "toolBarToggle", "freq": 6}, {"name": "closeAboutBox", "freq": 3}, {"name": "aboutBox", "freq": 2}, {"name": "appInit", "freq": 10}, {"name": "load", "freq": 7}, {"name": "treeStats", "freq": 2}, {"name": "resize", "freq": 14}, {"name": "closeColorPicker", "freq": 2}, {"name": "pickedColor", "freq": 2}, {"name": "closeErrorBox", "freq": 1}, {"name": "warning", "freq": 1}, {"name": "cbCategory", "freq": 2}, {"name": "slider", "freq": 1}, {"name": "cbPercent", "freq": 1}, {"name": "setTitle", "freq": 2}]}]}]